[{"league_id": "8d447944-5f62-4c34-85de-abb3a52e701b", "league_name": "Mexico. Liga de Expansion MX", "league_country": "mexico", "matches": [{"id": "44654eef-5811-4539-b976-707fb5e99d6c", "team_a": "Club Deportivo Mineros de Zacatecas", "team_b": "Tepatitlan de Morelos", "start_time": "LIVE", "url": "event/44654eef-5811-4539-b976-707fb5e99d6c", "team_a_image": null, "team_b_image": null, "match_country": "mexico", "league_name": "Mexico. Liga de Expansion MX", "c": "1"}]}, {"league_id": "f0b2ed90-249d-40ab-a170-b609f279e4b7", "league_name": "Mexico. Liga de Expansion", "league_country": "mexico", "matches": [{"id": "f8ccaa73-4878-460b-9b46-67f8bff69cac", "team_a": "Mineros de Zacatecas", "team_b": "Tepatitlan de Morelos", "start_time": 1600812000.0, "url": "event/f8ccaa73-4878-460b-9b46-67f8bff69cac", "team_a_image": "https://cdn.livetv341.me/img/teams/fullsize/29181.gif", "team_b_image": "https://cdn.livetv341.me/img/teams/fullsize/37345.gif", "match_country": "mexico", "league_name": "Mexico. Liga de Expansion", "c": "1"}, {"id": "347121a1-1f0b-4546-b1ed-7668d9d5ac20", "team_a": "Correcaminos", "team_b": "Cimarrones de Sonora", "start_time": 1600819500.0, "url": "event/347121a1-1f0b-4546-b1ed-7668d9d5ac20", "team_a_image": "https://cdn.livetv341.me/img/teams/fullsize/29186.gif", "team_b_image": "https://cdn.livetv341.me/img/teams/fullsize/43972.gif", "match_country": "mexico", "league_name": "Mexico. Liga de Expansion", "c": "1"}, {"id": "e70bf49d-3dc7-4985-9491-8584ef78aef8", "team_a": "Dorados", "team_b": "Cancun", "start_time": 1600826700.0, "url": "event/e70bf49d-3dc7-4985-9491-8584ef78aef8", "team_a_image": "https://cdn.livetv341.me/img/teams/fullsize/29185.gif", "team_b_image": "https://cdn.livetv341.me/img/teams/fullsize/43969.gif", "match_country": "mexico", "league_name": "Mexico. Liga de Expansion", "c": "1"}, {"id": "19a60160-a2e3-4a95-a468-cc0fc89e5223", "team_a": "Atlante", "team_b": "Tapatio", "start_time": 1600898400.0, "url": "event/19a60160-a2e3-4a95-a468-cc0fc89e5223", "team_a_image": "https://cdn.livetv341.me/img/teams/fullsize/11051.gif", "team_b_image": "https://cdn.livetv341.me/img/teams/fullsize/43971.gif", "match_country": "mexico", "league_name": "Mexico. Liga de Expansion", "c": "1"}]}, {"league_id": "f64cf7bc-5629-472c-9151-01b8f4db4bd2", "league_name": "Colombia. Primera A", "league_country": "colombia", "matches": [{"id": "f11eb1cc-736f-4788-befe-a99bf1b39fb9", "team_a": "Cucuta Deportivo", "team_b": "Deportivo Cali", "start_time": 1600821600.0, "url": "event/f11eb1cc-736f-4788-befe-a99bf1b39fb9", "team_a_image": "https://cdn.livetv341.me/img/teams/fullsize/10916.gif", "team_b_image": "https://cdn.livetv341.me/img/teams/fullsize/41415.gif", "match_country": "colombia", "league_name": "Colombia. Primera A", "c": "0"}]}, {"league_id": "0f114ad7-cc31-43d0-8865-46b56b9a8209", "league_name": "Italy. Cup", "league_country": "italy", "matches": [{"id": "b4297e9b-2132-4b0a-9f58-b52534515399", "team_a": "Piacenza", "team_b": "Teramo", "start_time": 1600867800.0, "url": "event/b4297e9b-2132-4b0a-9f58-b52534515399", "team_a_image": "https://cdn.livetv341.me/img/teams/fullsize/4945.gif", "team_b_image": "https://cdn.livetv341.me/img/teams/fullsize/13769.gif", "match_country": "italy", "league_name": "Italy. Cup", "c": "1"}, {"id": "433b6fff-cd05-4b88-afab-bb64dd4925e5", "team_a": "Carpi", "team_b": "Virtus Kazarano", "start_time": 1600869600.0, "url": "event/433b6fff-cd05-4b88-afab-bb64dd4925e5", "team_a_image": "https://cdn.livetv341.me/img/teams/fullsize/12533.gif", "team_b_image": "https://cdn.livetv341.me/img/teams/fullsize/44082.gif", "match_country": "italy", "league_name": "Italy. Cup", "c": "1"}, {"id": "62c50101-8a9f-430c-ba50-0bc70f0a099b", "team_a": "Novara", "team_b": "Gelbison", "start_time": 1600871400.0, "url": "event/62c50101-8a9f-430c-ba50-0bc70f0a099b", "team_a_image": "https://cdn.livetv341.me/img/teams/fullsize/10293.gif", "team_b_image": "https://cdn.livetv341.me/img/teams/fullsize/25484.gif", "match_country": "italy", "league_name": "Italy. Cup", "c": "1"}, {"id": "1e51de5f-6a6e-4f9a-bc9b-2f5a3dc068e4", "team_a": "Catanzaro", "team_b": "Virtus Francavilla", "start_time": 1600873200.0, "url": "event/1e51de5f-6a6e-4f9a-bc9b-2f5a3dc068e4", "team_a_image": "https://cdn.livetv341.me/img/teams/fullsize/24286.gif", "team_b_image": "https://cdn.livetv341.me/img/teams/fullsize/24287.gif", "match_country": "italy", "league_name": "Italy. Cup", "c": "1"}, {"id": "4396b620-0e5f-4641-bf06-e3011a7d9336", "team_a": "Pontedera", "team_b": "Arezzo", "start_time": 1600873200.0, "url": "event/4396b620-0e5f-4641-bf06-e3011a7d9336", "team_a_image": "https://cdn.livetv341.me/img/teams/fullsize/15523.gif", "team_b_image": "https://cdn.livetv341.me/img/teams/fullsize/21119.gif", "match_country": "italy", "league_name": "Italy. Cup", "c": "1"}]}, {"league_id": "91ae8d08-d0ef-4e2d-aa30-dfb774813c28", "league_name": "England. League Cup / \nThird Round.", "league_country": "england", "matches": [{"id": "83c8b2d8-6387-46e7-a8b3-43bd239b5848", "team_a": "Preston", "team_b": "Brighton & Hove", "start_time": 1600884000.0, "url": "event/83c8b2d8-6387-46e7-a8b3-43bd239b5848", "team_a_image": "https://cdn.livetv341.me/img/teams/fullsize/17577.gif", "team_b_image": "https://cdn.livetv341.me/img/teams/fullsize/32095.gif", "match_country": "england", "league_name": "England. League Cup / \nThird Round.", "c": "1"}, {"id": "c16d0892-e07f-4dcf-8bc0-c0a4c338014b", "team_a": "Morecambe", "team_b": "Newcastle", "start_time": 1600886700.0, "url": "event/c16d0892-e07f-4dcf-8bc0-c0a4c338014b", "team_a_image": "https://cdn.livetv341.me/img/teams/fullsize/9500.gif", "team_b_image": "https://cdn.livetv341.me/img/teams/fullsize/32106.gif", "match_country": "england", "league_name": "England. League Cup / \nThird Round.", "c": "1"}, {"id": "0bedbcff-bfc9-4866-a1d9-3d28fc0d0d82", "team_a": "Fulham", "team_b": "Sheffield Wednesday", "start_time": 1600886700.0, "url": "event/0bedbcff-bfc9-4866-a1d9-3d28fc0d0d82", "team_a_image": "https://cdn.livetv341.me/img/teams/fullsize/32100.gif", "team_b_image": "https://cdn.livetv341.me/img/teams/fullsize/21511.gif", "match_country": "england", "league_name": "England. League Cup / \nThird Round.", "c": "1"}, {"id": "193f57fe-a6d4-4ae5-9060-28fd247735d4", "team_a": "Leicester City", "team_b": "Arsenal", "start_time": 1600886700.0, "url": "event/193f57fe-a6d4-4ae5-9060-28fd247735d4", "team_a_image": "https://cdn.livetv341.me/img/teams/fullsize/32102.gif", "team_b_image": "https://cdn.livetv341.me/img/teams/fullsize/32015.gif", "match_country": "england", "league_name": "England. League Cup / \nThird Round.", "c": "1"}, {"id": "6be657ea-d46f-47df-b29b-483c0f76ffdc", "team_a": "Fleetwood Town", "team_b": "Everton", "start_time": 1600886700.0, "url": "event/6be657ea-d46f-47df-b29b-483c0f76ffdc", "team_a_image": "https://cdn.livetv341.me/img/teams/fullsize/11511.gif", "team_b_image": "https://cdn.livetv341.me/img/teams/fullsize/32099.gif", "match_country": "england", "league_name": "England. League Cup / \nThird Round.", "c": "1"}, {"id": "514c8360-ee90-4d95-9fea-5515c16c2d99", "team_a": "Chelsea", "team_b": "Barnsley", "start_time": 1600886700.0, "url": "event/514c8360-ee90-4d95-9fea-5515c16c2d99", "team_a_image": "https://cdn.livetv341.me/img/teams/fullsize/32097.gif", "team_b_image": "https://cdn.livetv341.me/img/teams/fullsize/10397.gif", "match_country": "england", "league_name": "England. League Cup / \nThird Round.", "c": "1"}]}, {"league_id": "947fdeaa-fc07-4136-8d9a-95193b72e4cc", "league_name": "Portugal. LigaPro", "league_country": "portugal", "matches": [{"id": "80ed425a-7bbe-452f-8972-1ca52daa0ae6", "team_a": "Leixoes", "team_b": "Mafra", "start_time": 1600887600.0, "url": "event/80ed425a-7bbe-452f-8972-1ca52daa0ae6", "team_a_image": "https://cdn.livetv341.me/img/teams/fullsize/17797.gif", "team_b_image": "https://cdn.livetv341.me/img/teams/fullsize/21641.gif", "match_country": "portugal", "league_name": "Portugal. LigaPro", "c": "1"}]}, {"league_id": "120295e9-d786-43a4-a865-7484686c849b", "league_name": "Brazil. Campeonato Brasileiro B", "league_country": "brazil", "matches": [{"id": "82c9adaa-6116-47a0-a0d6-cac51f25b5b3", "team_a": "Operario Ferroviario", "team_b": "Cuiaba", "start_time": "LIVE", "url": "event/82c9adaa-6116-47a0-a0d6-cac51f25b5b3", "team_a_image": null, "team_b_image": null, "match_country": "brazil", "league_name": "Brazil. Campeonato Brasileiro B", "c": "1"}]}, {"league_id": "b0a27043-44fa-4b28-b428-e88785cd253c", "league_name": "Brazil. Copa do Brasil", "league_country": "brazil", "matches": [{"id": "d8a4df26-3e6a-4ccf-abc8-3bbe11a477e2", "team_a": "CRB Maceio", "team_b": "Esporte Clube Juventude", "start_time": "LIVE", "url": "event/d8a4df26-3e6a-4ccf-abc8-3bbe11a477e2", "team_a_image": null, "team_b_image": null, "match_country": "brazil", "league_name": "Brazil. Copa do Brasil", "c": "1"}]}, {"league_id": "af7147fb-4a27-4581-9071-bd7d914a056e", "league_name": "Brazil. Cup / \nFourth Round.", "league_country": "brazil", "matches": [{"id": "7b7da0a9-bf08-4dd4-b135-dae4c704af55", "team_a": "Regatas", "team_b": "Juventude", "start_time": 1600812000.0, "url": "event/7b7da0a9-bf08-4dd4-b135-dae4c704af55", "team_a_image": "https://cdn.livetv341.me/img/teams/fullsize/41379.gif", "team_b_image": "https://cdn.livetv341.me/img/teams/fullsize/5883.gif", "match_country": "brazil", "league_name": "Brazil. Cup / \nFourth Round.", "c": "1"}, {"id": "f36344cf-41f9-416e-9fd1-c1e3414c6588", "team_a": "America Mineiro", "team_b": "Ponte Preta", "start_time": 1600821000.0, "url": "event/f36344cf-41f9-416e-9fd1-c1e3414c6588", "team_a_image": "https://cdn.livetv341.me/img/teams/fullsize/41378.gif", "team_b_image": "https://cdn.livetv341.me/img/teams/fullsize/11195.gif", "match_country": "brazil", "league_name": "Brazil. Cup / \nFourth Round.", "c": "1"}]}, {"league_id": "703ee45a-74d5-445c-833a-1c91668dfd81", "league_name": "Brazil. Serie B", "league_country": "brazil", "matches": [{"id": "a5bccc66-a301-4d8d-bf82-f5c34443da59", "team_a": "Operario Ferroviario EC", "team_b": "Cuiaba", "start_time": 1600815600.0, "url": "event/a5bccc66-a301-4d8d-bf82-f5c34443da59", "team_a_image": "https://cdn.livetv341.me/img/teams/fullsize/42599.gif", "team_b_image": "https://cdn.livetv341.me/img/teams/fullsize/41380.gif", "match_country": "brazil", "league_name": "Brazil. Serie B", "c": "1"}]}, {"league_id": "48918e62-7736-4806-8d23-6b82789ab188", "league_name": "Russia. Youth League", "league_country": "russia", "matches": [{"id": "39458377-3423-4bca-975a-a6264c5b7d2d", "team_a": "Ural U19", "team_b": "Akademiya Konoplev U19", "start_time": 1600844400.0, "url": "event/39458377-3423-4bca-975a-a6264c5b7d2d", "team_a_image": "https://cdn.livetv341.me/img/teams/fullsize/15260.gif", "team_b_image": "https://cdn.livetv341.me/img/teams/fullsize/44206.gif", "match_country": "russia", "league_name": "Russia. Youth League", "c": "1"}, {"id": "c98717d0-9bb3-4ab6-b16e-fb96fcb1a626", "team_a": "Dynamo Moscow U19", "team_b": "Akhmat U19", "start_time": 1600855200.0, "url": "event/c98717d0-9bb3-4ab6-b16e-fb96fcb1a626", "team_a_image": "https://cdn.livetv341.me/img/teams/fullsize/15808.gif", "team_b_image": "https://cdn.livetv341.me/img/teams/fullsize/27785.gif", "match_country": "russia", "league_name": "Russia. Youth League", "c": "1"}, {"id": "13330fbd-a441-4198-938d-3a703750fa14", "team_a": "Zenit U19", "team_b": "UOR 5 Yegoryevsk U19", "start_time": 1600855200.0, "url": "event/13330fbd-a441-4198-938d-3a703750fa14", "team_a_image": "https://cdn.livetv341.me/img/teams/fullsize/15255.gif", "team_b_image": "https://cdn.livetv341.me/img/teams/fullsize/44207.gif", "match_country": "russia", "league_name": "Russia. Youth League", "c": "1"}, {"id": "37712f1e-ff25-4bf8-a6c8-7ad4568a05db", "team_a": "Spartak M U19", "team_b": "Tambov U19", "start_time": 1600858800.0, "url": "event/37712f1e-ff25-4bf8-a6c8-7ad4568a05db", "team_a_image": "https://cdn.livetv341.me/img/teams/fullsize/17825.gif", "team_b_image": "https://cdn.livetv341.me/img/teams/fullsize/37874.gif", "match_country": "russia", "league_name": "Russia. Youth League", "c": "1"}, {"id": "9b1c08d1-c84b-4eea-ba35-d0c9f1e14ecb", "team_a": "Lokomotiv M U19", "team_b": "Rubin U19", "start_time": 1600858800.0, "url": "event/9b1c08d1-c84b-4eea-ba35-d0c9f1e14ecb", "team_a_image": "https://cdn.livetv341.me/img/teams/fullsize/11090.gif", "team_b_image": "https://cdn.livetv341.me/img/teams/fullsize/17824.gif", "match_country": "russia", "league_name": "Russia. Youth League", "c": "1"}, {"id": "fea40344-986d-464f-94b6-d3aca9874667", "team_a": "CSKA Moscow U19", "team_b": "Ufa U19", "start_time": 1600858800.0, "url": "event/fea40344-986d-464f-94b6-d3aca9874667", "team_a_image": "https://cdn.livetv341.me/img/teams/fullsize/11095.gif", "team_b_image": "https://cdn.livetv341.me/img/teams/fullsize/16985.gif", "match_country": "russia", "league_name": "Russia. Youth League", "c": "1"}, {"id": "faeb3055-3034-4c03-ac68-11c438329191", "team_a": "Rotor U19", "team_b": "Krasnodar U19", "start_time": 1600862400.0, "url": "event/faeb3055-3034-4c03-ac68-11c438329191", "team_a_image": "https://cdn.livetv341.me/img/teams/fullsize/44205.gif", "team_b_image": "https://cdn.livetv341.me/img/teams/fullsize/11088.gif", "match_country": "russia", "league_name": "Russia. Youth League", "c": "1"}, {"id": "cabc3778-e97d-4a2b-b4d2-779701fdb320", "team_a": "Strogino U19", "team_b": "Khimki U19", "start_time": 1600862400.0, "url": "event/cabc3778-e97d-4a2b-b4d2-779701fdb320", "team_a_image": "https://cdn.livetv341.me/img/teams/fullsize/44208.gif", "team_b_image": "https://cdn.livetv341.me/img/teams/fullsize/5869.gif", "match_country": "russia", "league_name": "Russia. Youth League", "c": "1"}, {"id": "746ad216-82b0-4939-88ff-4bdd0557747e", "team_a": "Rostov U19", "team_b": "Sochi U19", "start_time": 1600869600.0, "url": "event/746ad216-82b0-4939-88ff-4bdd0557747e", "team_a_image": "https://cdn.livetv341.me/img/teams/fullsize/17823.gif", "team_b_image": "https://cdn.livetv341.me/img/teams/fullsize/37873.gif", "match_country": "russia", "league_name": "Russia. Youth League", "c": "1"}]}, {"league_id": "e886c4c0-79b7-4c84-bdd5-8355f2116d5d", "league_name": "Russia. Pervenstvo FNL", "league_country": "russia", "matches": [{"id": "6028ad70-f713-4c96-983f-9857c2ff595e", "team_a": "Krasnodar II", "team_b": "Orenburg", "start_time": 1600864200.0, "url": "event/6028ad70-f713-4c96-983f-9857c2ff595e", "team_a_image": "https://cdn.livetv341.me/img/teams/fullsize/17841.gif", "team_b_image": "https://cdn.livetv341.me/img/teams/fullsize/32176.gif", "match_country": "russia", "league_name": "Russia. Pervenstvo FNL", "c": "1"}, {"id": "72d0742e-0a31-44ce-b08a-af81b5dbfb12", "team_a": "Volgar", "team_b": "Irtysh", "start_time": 1600871400.0, "url": "event/72d0742e-0a31-44ce-b08a-af81b5dbfb12", "team_a_image": "https://cdn.livetv341.me/img/teams/fullsize/40359.gif", "team_b_image": "https://cdn.livetv341.me/img/teams/fullsize/30547.gif", "match_country": "russia", "league_name": "Russia. Pervenstvo FNL", "c": "1"}, {"id": "6372b7a1-26de-4ffb-b422-07e20a3daa78", "team_a": "Neftekhimik", "team_b": "Tekstilshchik Iv", "start_time": 1600873200.0, "url": "event/6372b7a1-26de-4ffb-b422-07e20a3daa78", "team_a_image": "https://cdn.livetv341.me/img/teams/fullsize/17842.gif", "team_b_image": "https://cdn.livetv341.me/img/teams/fullsize/9345.gif", "match_country": "russia", "league_name": "Russia. Pervenstvo FNL", "c": "1"}, {"id": "83da2b7e-b3bc-46ed-bb21-051e21f96236", "team_a": "Krylia Sovetov", "team_b": "Dinamo Briansk", "start_time": 1600873200.0, "url": "event/83da2b7e-b3bc-46ed-bb21-051e21f96236", "team_a_image": "https://cdn.livetv341.me/img/teams/fullsize/32174.gif", "team_b_image": "https://cdn.livetv341.me/img/teams/fullsize/32791.gif", "match_country": "russia", "league_name": "Russia. Pervenstvo FNL", "c": "1"}, {"id": "76c16007-fa33-4a83-93ad-4375d9975ec1", "team_a": "Shinnik", "team_b": "Chertanovo", "start_time": 1600875000.0, "url": "event/76c16007-fa33-4a83-93ad-4375d9975ec1", "team_a_image": "https://cdn.livetv341.me/img/teams/fullsize/10793.gif", "team_b_image": "https://cdn.livetv341.me/img/teams/fullsize/16987.gif", "match_country": "russia", "league_name": "Russia. Pervenstvo FNL", "c": "1"}, {"id": "0ed98158-8284-46b5-b9e8-a964bc7228a2", "team_a": "Alaniya", "team_b": "Spartak M II", "start_time": 1600876800.0, "url": "event/0ed98158-8284-46b5-b9e8-a964bc7228a2", "team_a_image": "https://cdn.livetv341.me/img/teams/fullsize/17838.gif", "team_b_image": "https://cdn.livetv341.me/img/teams/fullsize/15156.gif", "match_country": "russia", "league_name": "Russia. Pervenstvo FNL", "c": "1"}, {"id": "3ade7919-50fd-4ec8-bdc3-2b42c4c88419", "team_a": "Fakel", "team_b": "Tom", "start_time": 1600876800.0, "url": "event/3ade7919-50fd-4ec8-bdc3-2b42c4c88419", "team_a_image": "https://cdn.livetv341.me/img/teams/fullsize/10791.gif", "team_b_image": "https://cdn.livetv341.me/img/teams/fullsize/7252.gif", "match_country": "russia", "league_name": "Russia. Pervenstvo FNL", "c": "1"}, {"id": "236b4e83-c3d4-4d10-98bc-11075aa1d71a", "team_a": "Veles Moscow", "team_b": "SKA-Khabarovsk", "start_time": 1600876800.0, "url": "event/236b4e83-c3d4-4d10-98bc-11075aa1d71a", "team_a_image": "https://cdn.livetv341.me/img/teams/fullsize/27767.gif", "team_b_image": "https://cdn.livetv341.me/img/teams/fullsize/41358.gif", "match_country": "russia", "league_name": "Russia. Pervenstvo FNL", "c": "1"}, {"id": "fb1e8d48-2c08-431d-9a84-8676e706e0c4", "team_a": "Torpedo M", "team_b": "Nizhnyi Novgorod", "start_time": 1600878600.0, "url": "event/fb1e8d48-2c08-431d-9a84-8676e706e0c4", "team_a_image": "https://cdn.livetv341.me/img/teams/fullsize/41359.gif", "team_b_image": "https://cdn.livetv341.me/img/teams/fullsize/32086.gif", "match_country": "russia", "league_name": "Russia. Pervenstvo FNL", "c": "1"}, {"id": "087697a8-b0f6-45eb-a5bb-852b12021258", "team_a": "Baltika", "team_b": "Chayka P", "start_time": 1600880400.0, "url": "event/087697a8-b0f6-45eb-a5bb-852b12021258", "team_a_image": "https://cdn.livetv341.me/img/teams/fullsize/7529.gif", "team_b_image": "https://cdn.livetv341.me/img/teams/fullsize/43918.gif", "match_country": "russia", "league_name": "Russia. Pervenstvo FNL", "c": "1"}]}, {"league_id": "75073b16-7f04-4ea3-887c-d2a4690c6499", "league_name": "Russia. Cup", "league_country": "russia", "matches": [{"id": "87964ade-3afc-4974-9d8c-8877069f9b0c", "team_a": "Salyut-Belgorod", "team_b": "Arsenal-Tula", "start_time": 1600869600.0, "url": "event/87964ade-3afc-4974-9d8c-8877069f9b0c", "team_a_image": "https://cdn.livetv341.me/img/teams/fullsize/40358.gif", "team_b_image": "https://cdn.livetv341.me/img/teams/fullsize/32171.gif", "match_country": "russia", "league_name": "Russia. Cup", "c": "1"}, {"id": "d31c6f2d-2d68-42e3-b4af-ce49a6f0243d", "team_a": "Dynamo Stavropol", "team_b": "Rotor", "start_time": 1600876800.0, "url": "event/d31c6f2d-2d68-42e3-b4af-ce49a6f0243d", "team_a_image": "https://cdn.livetv341.me/img/teams/fullsize/40360.gif", "team_b_image": "https://cdn.livetv341.me/img/teams/fullsize/34718.gif", "match_country": "russia", "league_name": "Russia. Cup", "c": "1"}]}, {"league_id": "46280a39-811b-40ab-b7a5-b1fcec58e94b", "league_name": "Mongolia. Premier League", "league_country": "mongolia", "matches": [{"id": "78658db6-2ffe-4ff5-887b-049fba25e482", "team_a": "Ulaanbaatar City", "team_b": "Anduud City", "start_time": 1600848000.0, "url": "event/78658db6-2ffe-4ff5-887b-049fba25e482", "team_a_image": "https://cdn.livetv341.me/img/teams/fullsize/28650.gif", "team_b_image": "https://cdn.livetv341.me/img/teams/fullsize/43503.gif", "match_country": "mongolia", "league_name": "Mongolia. Premier League", "c": "1"}, {"id": "1e0378e8-6693-4d3a-bf80-2eb09c678a2f", "team_a": "Khaan Khuns-Erchim", "team_b": "Ulaanbaatar", "start_time": 1600858800.0, "url": "event/1e0378e8-6693-4d3a-bf80-2eb09c678a2f", "team_a_image": null, "team_b_image": null, "match_country": "mongolia", "league_name": "Mongolia. Premier League", "c": "1"}]}, {"league_id": "e34e9ed7-0792-49d1-bbee-8a5ec0f8c16f", "league_name": "Japan. J League", "league_country": "japan", "matches": [{"id": "5fbff3f0-0740-4ca4-88c5-49b2a02168f9", "team_a": "Consadole Sapporo", "team_b": "Kashiwa", "start_time": 1600853400.0, "url": "event/5fbff3f0-0740-4ca4-88c5-49b2a02168f9", "team_a_image": "https://cdn.livetv341.me/img/teams/fullsize/33217.gif", "team_b_image": "https://cdn.livetv341.me/img/teams/fullsize/33224.gif", "match_country": "japan", "league_name": "Japan. J League", "c": "1"}, {"id": "d8b46f28-24ba-49e7-9654-15587c407ae1", "team_a": "Kashima", "team_b": "Shonan Bellmare", "start_time": 1600855200.0, "url": "event/d8b46f28-24ba-49e7-9654-15587c407ae1", "team_a_image": "https://cdn.livetv341.me/img/teams/fullsize/33218.gif", "team_b_image": "https://cdn.livetv341.me/img/teams/fullsize/33223.gif", "match_country": "japan", "league_name": "Japan. J League", "c": "1"}, {"id": "c64bee38-9257-488b-8f20-6e6aa449c396", "team_a": "Tokyo", "team_b": "Cerezo Osaka", "start_time": 1600855200.0, "url": "event/c64bee38-9257-488b-8f20-6e6aa449c396", "team_a_image": "https://cdn.livetv341.me/img/teams/fullsize/33214.gif", "team_b_image": "https://cdn.livetv341.me/img/teams/fullsize/33216.gif", "match_country": "japan", "league_name": "Japan. J League", "c": "1"}, {"id": "e3942696-1647-4e79-8e98-24431e519145", "team_a": "Kawasaki", "team_b": "Yokohama FC", "start_time": 1600855200.0, "url": "event/e3942696-1647-4e79-8e98-24431e519145", "team_a_image": "https://cdn.livetv341.me/img/teams/fullsize/33213.gif", "team_b_image": "https://cdn.livetv341.me/img/teams/fullsize/15661.gif", "match_country": "japan", "league_name": "Japan. J League", "c": "1"}, {"id": "f0d9513d-ad96-4476-8a47-d465ccaab883", "team_a": "Gamba Osaka", "team_b": "Nagoya", "start_time": 1600855200.0, "url": "event/f0d9513d-ad96-4476-8a47-d465ccaab883", "team_a_image": "https://cdn.livetv341.me/img/teams/fullsize/33228.gif", "team_b_image": "https://cdn.livetv341.me/img/teams/fullsize/33225.gif", "match_country": "japan", "league_name": "Japan. J League", "c": "1"}, {"id": "fd2ee6e4-1467-420a-8509-51a104ce7ea1", "team_a": "Vissel Kobe", "team_b": "Sagan Tosu", "start_time": 1600855200.0, "url": "event/fd2ee6e4-1467-420a-8509-51a104ce7ea1", "team_a_image": "https://cdn.livetv341.me/img/teams/fullsize/33215.gif", "team_b_image": "https://cdn.livetv341.me/img/teams/fullsize/33227.gif", "match_country": "japan", "league_name": "Japan. J League", "c": "1"}, {"id": "bdf9eca4-c7fc-4ba6-923c-4a5de837bf9e", "team_a": "Oita Trinita", "team_b": "Hiroshima", "start_time": 1600855200.0, "url": "event/bdf9eca4-c7fc-4ba6-923c-4a5de837bf9e", "team_a_image": "https://cdn.livetv341.me/img/teams/fullsize/402.gif", "team_b_image": "https://cdn.livetv341.me/img/teams/fullsize/33212.gif", "match_country": "japan", "league_name": "Japan. J League", "c": "1"}, {"id": "ae6ce671-fd67-4163-b7c5-e9e320300cc9", "team_a": "Yokohama Marinos", "team_b": "Sendai", "start_time": 1600857000.0, "url": "event/ae6ce671-fd67-4163-b7c5-e9e320300cc9", "team_a_image": "https://cdn.livetv341.me/img/teams/fullsize/33226.gif", "team_b_image": "https://cdn.livetv341.me/img/teams/fullsize/33219.gif", "match_country": "japan", "league_name": "Japan. J League", "c": "1"}, {"id": "d76aa826-79ad-4821-8286-e0fe2eb90839", "team_a": "Shimizu S-Pulse", "team_b": "Urawa Red Diamonds", "start_time": 1600857000.0, "url": "event/d76aa826-79ad-4821-8286-e0fe2eb90839", "team_a_image": "https://cdn.livetv341.me/img/teams/fullsize/39635.gif", "team_b_image": "https://cdn.livetv341.me/img/teams/fullsize/33220.gif", "match_country": "japan", "league_name": "Japan. J League", "c": "0"}]}, {"league_id": "c8dd2ada-7800-49b9-ba6c-0200271249d4", "league_name": "Japan. J2 League", "league_country": "japan", "matches": [{"id": "3c8de2c9-26d5-427a-9796-f41b1184c183", "team_a": "Kyoto", "team_b": "Tochigi", "start_time": 1600853400.0, "url": "event/3c8de2c9-26d5-427a-9796-f41b1184c183", "team_a_image": "https://cdn.livetv341.me/img/teams/fullsize/409.gif", "team_b_image": "https://cdn.livetv341.me/img/teams/fullsize/15659.gif", "match_country": "japan", "league_name": "Japan. J2 League", "c": "1"}, {"id": "c7fcea79-fe31-4f3c-9b95-8cc073d0f623", "team_a": "Omiya", "team_b": "Tokushima Vortis", "start_time": 1600855200.0, "url": "event/c7fcea79-fe31-4f3c-9b95-8cc073d0f623", "team_a_image": "https://cdn.livetv341.me/img/teams/fullsize/10604.gif", "team_b_image": "https://cdn.livetv341.me/img/teams/fullsize/15658.gif", "match_country": "japan", "league_name": "Japan. J2 League", "c": "1"}, {"id": "f7094630-76e7-4b91-a6b0-31de48bf1f27", "team_a": "JEF United", "team_b": "Renofa", "start_time": 1600855200.0, "url": "event/f7094630-76e7-4b91-a6b0-31de48bf1f27", "team_a_image": "https://cdn.livetv341.me/img/teams/fullsize/15109.gif", "team_b_image": "https://cdn.livetv341.me/img/teams/fullsize/21531.gif", "match_country": "japan", "league_name": "Japan. J2 League", "c": "1"}, {"id": "cea748a1-c05d-404a-8e94-ff45ac8befa1", "team_a": "Machida Zelvia", "team_b": "V-Varen Nagasaki", "start_time": 1600855200.0, "url": "event/cea748a1-c05d-404a-8e94-ff45ac8befa1", "team_a_image": "https://cdn.livetv341.me/img/teams/fullsize/21532.gif", "team_b_image": "https://cdn.livetv341.me/img/teams/fullsize/33229.gif", "match_country": "japan", "league_name": "Japan. J2 League", "c": "1"}, {"id": "bdb1495d-57d7-4520-b110-f44746bb7ae0", "team_a": "Matsumoto Yamaga", "team_b": "Ryukyu", "start_time": 1600855200.0, "url": "event/bdb1495d-57d7-4520-b110-f44746bb7ae0", "team_a_image": "https://cdn.livetv341.me/img/teams/fullsize/15668.gif", "team_b_image": "https://cdn.livetv341.me/img/teams/fullsize/22687.gif", "match_country": "japan", "league_name": "Japan. J2 League", "c": "1"}, {"id": "2d4887f7-fe3b-41a2-be20-86beec84b6ec", "team_a": "Zweigen Kanazawa", "team_b": "Tokyo Verdy", "start_time": 1600855200.0, "url": "event/2d4887f7-fe3b-41a2-be20-86beec84b6ec", "team_a_image": "https://cdn.livetv341.me/img/teams/fullsize/20873.gif", "team_b_image": "https://cdn.livetv341.me/img/teams/fullsize/408.gif", "match_country": "japan", "league_name": "Japan. J2 League", "c": "1"}, {"id": "8fec5ce5-1e4d-433b-a3f8-832a20f20f98", "team_a": "Fagiano Okayama", "team_b": "Montedio Yamagata", "start_time": 1600855200.0, "url": "event/8fec5ce5-1e4d-433b-a3f8-832a20f20f98", "team_a_image": "https://cdn.livetv341.me/img/teams/fullsize/15665.gif", "team_b_image": "https://cdn.livetv341.me/img/teams/fullsize/15662.gif", "match_country": "japan", "league_name": "Japan. J2 League", "c": "1"}, {"id": "75f8feb8-531f-4106-b26f-8721840a8558", "team_a": "Ehime", "team_b": "Albirex Niigata", "start_time": 1600855200.0, "url": "event/75f8feb8-531f-4106-b26f-8721840a8558", "team_a_image": "https://cdn.livetv341.me/img/teams/fullsize/15663.gif", "team_b_image": "https://cdn.livetv341.me/img/teams/fullsize/33815.gif", "match_country": "japan", "league_name": "Japan. J2 League", "c": "1"}, {"id": "185759a7-d970-4e75-8828-d337b6ed23ed", "team_a": "Fukuoka", "team_b": "Thespa Kusatsu", "start_time": 1600855200.0, "url": "event/185759a7-d970-4e75-8828-d337b6ed23ed", "team_a_image": "https://cdn.livetv341.me/img/teams/fullsize/10605.gif", "team_b_image": "https://cdn.livetv341.me/img/teams/fullsize/15656.gif", "match_country": "japan", "league_name": "Japan. J2 League", "c": "1"}, {"id": "4a4473a3-425d-41c4-912a-be479f093300", "team_a": "Giravanz Kitakyushu", "team_b": "Mito Hollyhock", "start_time": 1600855200.0, "url": "event/4a4473a3-425d-41c4-912a-be479f093300", "team_a_image": "https://cdn.livetv341.me/img/teams/fullsize/15666.gif", "team_b_image": "https://cdn.livetv341.me/img/teams/fullsize/15657.gif", "match_country": "japan", "league_name": "Japan. J2 League", "c": "1"}, {"id": "5d13ec5d-3fb4-46b4-94c0-a34b0702f9a3", "team_a": "Iwata", "team_b": "Kofu", "start_time": 1600857000.0, "url": "event/5d13ec5d-3fb4-46b4-94c0-a34b0702f9a3", "team_a_image": "https://cdn.livetv341.me/img/teams/fullsize/33221.gif", "team_b_image": "https://cdn.livetv341.me/img/teams/fullsize/8562.gif", "match_country": "japan", "league_name": "Japan. J2 League", "c": "1"}]}, {"league_id": "0486ebcc-11d3-4669-aad2-0f94227ea37c", "league_name": "Kazakhstan. Premier League", "league_country": "kazakhstan", "matches": [{"id": "56050c09-d5c2-405a-8485-4bdaaccfb6e4", "team_a": "Kaspiy", "team_b": "Taraz", "start_time": 1600853400.0, "url": "event/56050c09-d5c2-405a-8485-4bdaaccfb6e4", "team_a_image": "https://cdn.livetv341.me/img/teams/fullsize/31688.gif", "team_b_image": "https://cdn.livetv341.me/img/teams/fullsize/17699.gif", "match_country": "kazakhstan", "league_name": "Kazakhstan. Premier League", "c": "1"}]}, {"league_id": "88a70cef-fe1a-46a2-b11c-f1ed4d90c222", "league_name": "South Korea. Cup / \nSemifinal.", "league_country": "south-korea", "matches": [{"id": "b3d80db6-8af1-4424-b4b3-d3056d78dda8", "team_a": "Jeonbuk Motors", "team_b": "Seongnam", "start_time": 1600855200.0, "url": "event/b3d80db6-8af1-4424-b4b3-d3056d78dda8", "team_a_image": "https://cdn.livetv341.me/img/teams/fullsize/33291.gif", "team_b_image": "https://cdn.livetv341.me/img/teams/fullsize/21456.gif", "match_country": "south-korea", "league_name": "South Korea. Cup / \nSemifinal.", "c": "1"}, {"id": "49e488f0-ef68-40f6-bf9f-73ed353dfbbc", "team_a": "Ulsan", "team_b": "Pohang", "start_time": 1600857000.0, "url": "event/49e488f0-ef68-40f6-bf9f-73ed353dfbbc", "team_a_image": "https://cdn.livetv341.me/img/teams/fullsize/33293.gif", "team_b_image": "https://cdn.livetv341.me/img/teams/fullsize/33295.gif", "match_country": "south-korea", "league_name": "South Korea. Cup / \nSemifinal.", "c": "1"}]}, {"league_id": "70c06dbc-2235-4cf1-a0ea-6010d9fadde3", "league_name": "Armenia. Premier League", "league_country": "armenia", "matches": [{"id": "61ab8709-c3b7-4ee2-b460-713a34d8b0fb", "team_a": "Lori", "team_b": "Pyunik", "start_time": 1600863300.0, "url": "event/61ab8709-c3b7-4ee2-b460-713a34d8b0fb", "team_a_image": "https://cdn.livetv341.me/img/teams/fullsize/32982.gif", "team_b_image": "https://cdn.livetv341.me/img/teams/fullsize/37908.gif", "match_country": "armenia", "league_name": "Armenia. Premier League", "c": "1"}, {"id": "5bf551c5-7eaf-4df7-abc2-5d4c9fd36eca", "team_a": "Gandzasar", "team_b": "Shirak", "start_time": 1600871400.0, "url": "event/5bf551c5-7eaf-4df7-abc2-5d4c9fd36eca", "team_a_image": "https://cdn.livetv341.me/img/teams/fullsize/32984.gif", "team_b_image": "https://cdn.livetv341.me/img/teams/fullsize/32980.gif", "match_country": "armenia", "league_name": "Armenia. Premier League", "c": "1"}]}, {"league_id": "28c47b5e-7839-49b1-8252-1a89cf68c689", "league_name": "Belarus Premier League", "league_country": "belarus", "matches": [{"id": "f5ce31ea-c2a1-4483-a022-80a2c722d8cf", "team_a": "Smolevichi", "team_b": "Minsk", "start_time": 1600866000.0, "url": "event/f5ce31ea-c2a1-4483-a022-80a2c722d8cf", "team_a_image": "https://cdn.livetv341.me/img/teams/fullsize/41391.gif", "team_b_image": "https://cdn.livetv341.me/img/teams/fullsize/32891.gif", "match_country": "belarus", "league_name": "Belarus. Vysheyshaya Liga", "c": "1"}]}, {"league_id": "d1f59fad-5d86-41c8-97d0-be64ec51a4b6", "league_name": "Moldova. National Division", "league_country": "moldova", "matches": [{"id": "12d4864b-3191-40b0-8068-5963d40aac6e", "team_a": "Zimbru", "team_b": "Speranta Nisporeni", "start_time": 1600866000.0, "url": "event/12d4864b-3191-40b0-8068-5963d40aac6e", "team_a_image": "https://cdn.livetv341.me/img/teams/fullsize/33827.gif", "team_b_image": "https://cdn.livetv341.me/img/teams/fullsize/37925.gif", "match_country": "moldova", "league_name": "Moldova. National Division", "c": "1"}]}, {"league_id": "63907a1d-968a-4863-b552-7f23688d8c14", "league_name": "2. Liga", "league_country": "slovakia", "matches": [{"id": "0a6cee9b-2ce4-4c60-8128-558a54f9cf34", "team_a": "Zilina II", "team_b": "Slavoj Trebisov", "start_time": 1600867800.0, "url": "event/0a6cee9b-2ce4-4c60-8128-558a54f9cf34", "team_a_image": "https://cdn.livetv341.me/img/teams/fullsize/22022.gif", "team_b_image": "https://cdn.livetv341.me/img/teams/fullsize/22253.gif", "match_country": "slovakia", "league_name": "Slovakia. 2. Liga", "c": "1"}]}, {"league_id": "9eecde2a-1551-4442-b13f-dcfa203588c3", "league_name": "Jordan. Premier League", "league_country": "jordan", "matches": [{"id": "992da0d1-63c7-438b-bab1-d4d08bf9f189", "team_a": "Al Jazeera", "team_b": "Maan", "start_time": 1600869600.0, "url": "event/992da0d1-63c7-438b-bab1-d4d08bf9f189", "team_a_image": "https://cdn.livetv341.me/img/teams/fullsize/33467.gif", "team_b_image": "https://cdn.livetv341.me/img/teams/fullsize/43688.gif", "match_country": "jordan", "league_name": "Jordan. Premier League", "c": "1"}, {"id": "0400fd4c-f280-482c-819d-ace31711b9af", "team_a": "Sahab", "team_b": "Al Wihdat", "start_time": 1600878600.0, "url": "event/0400fd4c-f280-482c-819d-ace31711b9af", "team_a_image": "https://cdn.livetv341.me/img/teams/fullsize/23063.gif", "team_b_image": "https://cdn.livetv341.me/img/teams/fullsize/33465.gif", "match_country": "jordan", "league_name": "Jordan. Premier League", "c": "1"}]}, {"league_id": "f2c6c6e8-3428-49ea-8b97-8d03606c92ce", "league_name": "Finland. Veikkausliiga", "league_country": "finland", "matches": [{"id": "41f01fe9-6da0-4f7d-b09c-2b557e4995f6", "team_a": "Jaca", "team_b": "RoPS", "start_time": 1600875000.0, "url": "event/41f01fe9-6da0-4f7d-b09c-2b557e4995f6", "team_a_image": "https://cdn.livetv341.me/img/teams/fullsize/17593.gif", "team_b_image": "https://cdn.livetv341.me/img/teams/fullsize/32826.gif", "match_country": "finland", "league_name": "Finland. Veikkausliiga", "c": "1"}, {"id": "93a15194-d46d-4f14-abda-53ad05f7dd15", "team_a": "Inter Turku", "team_b": "Honka", "start_time": 1600875000.0, "url": "event/93a15194-d46d-4f14-abda-53ad05f7dd15", "team_a_image": "https://cdn.livetv341.me/img/teams/fullsize/32829.gif", "team_b_image": "https://cdn.livetv341.me/img/teams/fullsize/33161.gif", "match_country": "finland", "league_name": "Finland. Veikkausliiga", "c": "1"}, {"id": "c9e48294-2b79-4457-be77-a13e41e40838", "team_a": "Mariehamn", "team_b": "Ilves", "start_time": 1600875000.0, "url": "event/c9e48294-2b79-4457-be77-a13e41e40838", "team_a_image": "https://cdn.livetv341.me/img/teams/fullsize/32831.gif", "team_b_image": "https://cdn.livetv341.me/img/teams/fullsize/32828.gif", "match_country": "finland", "league_name": "Finland. Veikkausliiga", "c": "1"}, {"id": "539cc1f2-6a61-4c62-b6ca-f242bde61fe7", "team_a": "KuPS Kuopio", "team_b": "HIFK", "start_time": 1600875000.0, "url": "event/539cc1f2-6a61-4c62-b6ca-f242bde61fe7", "team_a_image": "https://cdn.livetv341.me/img/teams/fullsize/32827.gif", "team_b_image": "https://cdn.livetv341.me/img/teams/fullsize/17594.gif", "match_country": "finland", "league_name": "Finland. Veikkausliiga", "c": "1"}, {"id": "ce9d1ddc-ab15-4a75-b2f9-89682ac81637", "team_a": "SJK", "team_b": "Lahti", "start_time": 1600875000.0, "url": "event/ce9d1ddc-ab15-4a75-b2f9-89682ac81637", "team_a_image": "https://cdn.livetv341.me/img/teams/fullsize/32830.gif", "team_b_image": "https://cdn.livetv341.me/img/teams/fullsize/32875.gif", "match_country": "finland", "league_name": "Finland. Veikkausliiga", "c": "1"}]}, {"league_id": "6a2e100c-173f-4ef6-a998-2d30e9ed6e72", "league_name": "Meistaradeildin", "league_country": "faroe-islands", "matches": [{"id": "9ce92a89-15e0-47b3-bb51-4594a546fc09", "team_a": "Tvoroyri", "team_b": "Runavik", "start_time": 1600875000.0, "url": "event/9ce92a89-15e0-47b3-bb51-4594a546fc09", "team_a_image": "https://cdn.livetv341.me/img/teams/fullsize/15503.gif", "team_b_image": "https://cdn.livetv341.me/img/teams/fullsize/12783.gif", "match_country": "faroe-islands", "league_name": "Faroe Islands. Premier League", "c": "1"}, {"id": "e548a8bf-312b-456a-adae-07cab30b9817", "team_a": "Vikingur", "team_b": "Argir", "start_time": 1600880400.0, "url": "event/e548a8bf-312b-456a-adae-07cab30b9817", "team_a_image": "https://cdn.livetv341.me/img/teams/fullsize/7388.gif", "team_b_image": "https://cdn.livetv341.me/img/teams/fullsize/15501.gif", "match_country": "faroe-islands", "league_name": "Faroe Islands. Premier League", "c": "1"}, {"id": "2e3938ce-1faf-4a9d-855d-7cff03914788", "team_a": "Streymur", "team_b": "Torshavn", "start_time": 1600884000.0, "url": "event/2e3938ce-1faf-4a9d-855d-7cff03914788", "team_a_image": "https://cdn.livetv341.me/img/teams/fullsize/40410.gif", "team_b_image": "https://cdn.livetv341.me/img/teams/fullsize/7383.gif", "match_country": "faroe-islands", "league_name": "Faroe Islands. Premier League", "c": "1"}, {"id": "157e863b-8479-4beb-b75d-07ea94d2dc7f", "team_a": "Skala Eysturoy", "team_b": "Fuglafjordur", "start_time": 1600884000.0, "url": "event/157e863b-8479-4beb-b75d-07ea94d2dc7f", "team_a_image": "https://cdn.livetv341.me/img/teams/fullsize/29145.gif", "team_b_image": "https://cdn.livetv341.me/img/teams/fullsize/9359.gif", "match_country": "faroe-islands", "league_name": "Faroe Islands. Premier League", "c": "1"}]}, {"league_id": "18322563-9ed6-4798-923e-7a6a9bd13efe", "league_name": "Ukraine. Premier League", "league_country": "ukraine", "matches": [{"id": "b1f3fff7-33cb-4f91-951a-1b2ccb6dde2b", "team_a": "Rukh Vinnyky", "team_b": "Shakhtar Donetsk", "start_time": 1600876800.0, "url": "event/b1f3fff7-33cb-4f91-951a-1b2ccb6dde2b", "team_a_image": "https://cdn.livetv341.me/img/teams/fullsize/39782.gif", "team_b_image": "https://cdn.livetv341.me/img/teams/fullsize/32620.gif", "match_country": "ukraine", "league_name": "Ukraine. Premier League", "c": "0"}]}, {"league_id": "d1e154be-b535-4093-b147-c5045d3843d8", "league_name": "Peru. Primera Division", "league_country": "peru", "matches": [{"id": "1075b34b-99a0-4e92-b76d-bcf6c9b93588", "team_a": "Alianza Universidad", "team_b": "Cusco", "start_time": 1600876800.0, "url": "event/1075b34b-99a0-4e92-b76d-bcf6c9b93588", "team_a_image": "https://cdn.livetv341.me/img/teams/fullsize/27230.gif", "team_b_image": "https://cdn.livetv341.me/img/teams/fullsize/41420.gif", "match_country": "peru", "league_name": "Peru. Primera Division", "c": "1"}, {"id": "35dc6083-2794-4d4d-928b-b85c398f29e4", "team_a": "Cienciano", "team_b": "Melgar", "start_time": 1600891200.0, "url": "event/35dc6083-2794-4d4d-928b-b85c398f29e4", "team_a_image": "https://cdn.livetv341.me/img/teams/fullsize/17776.gif", "team_b_image": "https://cdn.livetv341.me/img/teams/fullsize/33436.gif", "match_country": "peru", "league_name": "Peru. Primera Division", "c": "1"}, {"id": "ddab8185-e4cb-4f9f-b533-3810af9b7e7c", "team_a": "Deportivo Llacuabamba", "team_b": "Sporting Cristal", "start_time": 1600893000.0, "url": "event/ddab8185-e4cb-4f9f-b533-3810af9b7e7c", "team_a_image": "https://cdn.livetv341.me/img/teams/fullsize/39559.gif", "team_b_image": "https://cdn.livetv341.me/img/teams/fullsize/33440.gif", "match_country": "peru", "league_name": "Peru. Primera Division", "c": "1"}]}, {"league_id": "a556432b-2936-4795-83cc-fb61eeb8f574", "league_name": "Meistriliiga", "league_country": "estonia", "matches": [{"id": "5928e006-f652-4372-a022-fdafdf432c52", "team_a": "Tammeka", "team_b": "Kalju", "start_time": 1600876800.0, "url": "event/5928e006-f652-4372-a022-fdafdf432c52", "team_a_image": "https://cdn.livetv341.me/img/teams/fullsize/41388.gif", "team_b_image": "https://cdn.livetv341.me/img/teams/fullsize/39810.gif", "match_country": "estonia", "league_name": "Estonia. Meistriliiga", "c": "1"}]}, {"league_id": "4e3faadb-bbb7-492b-9582-b5d2ded9e3b7", "league_name": "Egypt. Premier League", "league_country": "egypt", "matches": [{"id": "71a557f8-d5bf-4880-872f-051e9ebb40a4", "team_a": "Masr", "team_b": "Al-Ahly Cairo", "start_time": 1600884000.0, "url": "event/71a557f8-d5bf-4880-872f-051e9ebb40a4", "team_a_image": "https://cdn.livetv341.me/img/teams/fullsize/38151.gif", "team_b_image": "https://cdn.livetv341.me/img/teams/fullsize/33470.gif", "match_country": "egypt", "league_name": "Egypt. Premier League", "c": "1"}]}, {"league_id": "a696ccd7-643d-4484-a3ee-0b59ef36485d", "league_name": "Morocco. Botola Pro", "league_country": "morocco", "matches": [{"id": "43dc2185-eb04-453e-b28b-89ea43630001", "team_a": "Ittihad Tanger", "team_b": "Khemis Zemamra", "start_time": 1600884900.0, "url": "event/43dc2185-eb04-453e-b28b-89ea43630001", "team_a_image": "https://cdn.livetv341.me/img/teams/fullsize/33311.gif", "team_b_image": "https://cdn.livetv341.me/img/teams/fullsize/38219.gif", "match_country": "morocco", "league_name": "Morocco. Botola Pro", "c": "1"}, {"id": "e2f6029d-cb9b-4b2b-907a-63824194b486", "team_a": "Berkane", "team_b": "FAR Rabat", "start_time": 1600893000.0, "url": "event/e2f6029d-cb9b-4b2b-907a-63824194b486", "team_a_image": "https://cdn.livetv341.me/img/teams/fullsize/33319.gif", "team_b_image": "https://cdn.livetv341.me/img/teams/fullsize/33317.gif", "match_country": "morocco", "league_name": "Morocco. Botola Pro", "c": "1"}]}, {"league_id": "cf0acd16-7d70-4d53-acb4-eb1b8b51d8ae", "league_name": "ACL Indoor", "league_country": "unknown", "matches": [{"id": "8e7d5e7c-136f-4014-8291-a819d8ac9b7f", "team_a": "Manchester City (ACL)", "team_b": "Borussia Dortmund (ACL)", "start_time": "LIVE", "url": "event/8e7d5e7c-136f-4014-8291-a819d8ac9b7f", "team_a_image": null, "team_b_image": null, "match_country": "unknown", "league_name": "ACL Indoor", "c": "0"}]}, {"league_id": "bef578a8-d9e9-4eca-91de-8e0da0c65f4c", "league_name": "Copa Libertadores", "league_country": "unknown", "matches": [{"id": "5406d68b-2342-4ec4-b8d7-2f03f059f4b1", "team_a": "Barcelona Sporting Club", "team_b": "Clube de Regatas do Flamengo", "start_time": "LIVE", "url": "event/5406d68b-2342-4ec4-b8d7-2f03f059f4b1", "team_a_image": null, "team_b_image": null, "match_country": "unknown", "league_name": "Copa Libertadores", "c": "1"}, {"id": "c0fb9eb5-3e41-4564-8a3a-483e4a4d0028", "team_a": "Barcelona Guayaquil", "team_b": "Flamengo", "start_time": 1600812900.0, "url": "event/c0fb9eb5-3e41-4564-8a3a-483e4a4d0028", "team_a_image": "https://cdn.livetv341.me/img/teams/fullsize/32835.gif", "team_b_image": "https://cdn.livetv341.me/img/teams/fullsize/32690.gif", "match_country": "unknown", "league_name": "Copa Libertadores", "c": "0"}, {"id": "6278614a-b44d-41fb-bfac-b4b17e255298", "team_a": "Junior", "team_b": "Independiente JT", "start_time": 1600821000.0, "url": "event/6278614a-b44d-41fb-bfac-b4b17e255298", "team_a_image": "https://cdn.livetv341.me/img/teams/fullsize/33061.gif", "team_b_image": "https://cdn.livetv341.me/img/teams/fullsize/32841.gif", "match_country": "unknown", "league_name": "Copa Libertadores", "c": "1"}, {"id": "84492104-9372-427d-9374-5e9dbc438696", "team_a": "Liga Deportiva Universitaria de Quito", "team_b": "Sao Paolo", "start_time": 1600821000.0, "url": "event/84492104-9372-427d-9374-5e9dbc438696", "team_a_image": "https://cdn.livetv341.me/img/teams/fullsize/32839.gif", "team_b_image": "https://cdn.livetv341.me/img/teams/fullsize/32689.gif", "match_country": "unknown", "league_name": "Copa Libertadores", "c": "0"}, {"id": "f7822b01-0259-439e-a5ce-7fec86b1ac8f", "team_a": "EM Deportivo Binacional", "team_b": "CA River Plate", "start_time": 1600821000.0, "url": "event/f7822b01-0259-439e-a5ce-7fec86b1ac8f", "team_a_image": "https://cdn.livetv341.me/img/teams/fullsize/33434.gif", "team_b_image": "https://cdn.livetv341.me/img/teams/fullsize/32634.gif", "match_country": "unknown", "league_name": "Copa Libertadores", "c": "0"}, {"id": "42595bbf-f503-4355-8e77-2f1f0fbae633", "team_a": "Defensa y Justicia", "team_b": "Club Olimpia", "start_time": 1600899300.0, "url": "event/42595bbf-f503-4355-8e77-2f1f0fbae633", "team_a_image": "https://cdn.livetv341.me/img/teams/fullsize/33069.gif", "team_b_image": "https://cdn.livetv341.me/img/teams/fullsize/33589.gif", "match_country": "unknown", "league_name": "Copa Libertadores", "c": "1"}, {"id": "09406655-2975-445f-bada-0a5dbfb7138e", "team_a": "Atletico-PR", "team_b": "Colo Colo", "start_time": 1600899300.0, "url": "event/09406655-2975-445f-bada-0a5dbfb7138e", "team_a_image": "https://cdn.livetv341.me/img/teams/fullsize/41346.gif", "team_b_image": "https://cdn.livetv341.me/img/teams/fullsize/33358.gif", "match_country": "unknown", "league_name": "Copa Libertadores", "c": "1"}, {"id": "ce3c5e7e-6d76-406c-a68b-c259b052286d", "team_a": "Caracas", "team_b": "Libertad", "start_time": 1600899300.0, "url": "event/ce3c5e7e-6d76-406c-a68b-c259b052286d", "team_a_image": "https://cdn.livetv341.me/img/teams/fullsize/33570.gif", "team_b_image": "https://cdn.livetv341.me/img/teams/fullsize/33592.gif", "match_country": "unknown", "league_name": "Copa Libertadores", "c": "1"}, {"id": "3b225420-8d17-47b9-860a-ef9fbecb9d2b", "team_a": "Estudiantes de Merida", "team_b": "Nacional", "start_time": "LIVE", "url": "event/3b225420-8d17-47b9-860a-ef9fbecb9d2b", "team_a_image": "https://cdn.livetv341.me/img/teams/fullsize/33560.gif", "team_b_image": "https://cdn.livetv341.me/img/teams/fullsize/33781.gif", "match_country": "unknown", "league_name": "Copa Libertadores", "c": "0"}, {"id": "1cce422e-93d6-4a1a-9a9b-95b442c12ac1", "team_a": "Tigre", "team_b": "Bolivar", "start_time": "LIVE", "url": "event/1cce422e-93d6-4a1a-9a9b-95b442c12ac1", "team_a_image": "https://cdn.livetv341.me/img/teams/fullsize/32645.gif", "team_b_image": "https://cdn.livetv341.me/img/teams/fullsize/32846.gif", "match_country": "unknown", "league_name": "South America. Copa Libertadores", "c": "0"}, {"id": "57e0d9d7-77a3-4bea-9d32-0812e862d985", "team_a": "Atletico Junior Barranquilla", "team_b": "Independiente del Valle", "start_time": 1600821000.0, "url": "event/57e0d9d7-77a3-4bea-9d32-0812e862d985", "team_a_image": null, "team_b_image": null, "match_country": "unknown", "league_name": "South America. Copa Libertadores", "c": "1"}, {"id": "1d2d6fc7-2566-4992-9b7a-c9e088778cfa", "team_a": "LDU Quito", "team_b": "Sao Paulo FC", "start_time": 1600821000.0, "url": "event/1d2d6fc7-2566-4992-9b7a-c9e088778cfa", "team_a_image": null, "team_b_image": null, "match_country": "unknown", "league_name": "South America. Copa Libertadores", "c": "1"}]}, {"league_id": "64790b4a-f92c-4c86-9275-0cc7147c0058", "league_name": "Derby League", "league_country": "unknown", "matches": [{"id": "e6dcd7e8-db51-493c-83bd-15e9477b1179", "team_a": "Galatasaray team", "team_b": "Sporting team", "start_time": "LIVE", "url": "event/e6dcd7e8-db51-493c-83bd-15e9477b1179", "team_a_image": null, "team_b_image": null, "match_country": "unknown", "league_name": "Derby League", "c": "0"}]}, {"league_id": "23c27878-0bf1-440e-bde5-3d0654ca8c1e", "league_name": "Dragon League 4.4", "league_country": "unknown", "matches": [{"id": "2b0cbb76-3c69-4169-a7b1-e681c7b2d656", "team_a": "Turkey (4\u00d1\u00854)", "team_b": "Sweden (4\u00d1\u00854)", "start_time": 1600826700.0, "url": "event/2b0cbb76-3c69-4169-a7b1-e681c7b2d656", "team_a_image": null, "team_b_image": null, "match_country": "unknown", "league_name": "Dragon League 4.4", "c": "0"}, {"id": "164d857a-dca8-467c-b95c-e2f9443892c0", "team_a": "Turkey (4\u0421\u20264)", "team_b": "Sweden (4\u0421\u20264)", "start_time": 1600815900.0, "url": "event/164d857a-dca8-467c-b95c-e2f9443892c0", "team_a_image": null, "team_b_image": null, "match_country": "unknown", "league_name": "Dragon League 4.4", "c": "0"}]}, {"league_id": "bb4f9c7b-8d0a-4e8b-acd5-41d852b3818d", "league_name": "PRO Soccer League", "league_country": "unknown", "matches": [{"id": "bbf7e9d5-70ca-4513-80af-2af94c0a01a9", "team_a": "Barcelona (3\u00d1\u00853)", "team_b": "Liverpool (3\u00d1\u00853)", "start_time": 1600827420.0, "url": "event/bbf7e9d5-70ca-4513-80af-2af94c0a01a9", "team_a_image": null, "team_b_image": null, "match_country": "unknown", "league_name": "PRO Soccer League", "c": "0"}, {"id": "2371f474-d872-4623-9bc6-e580be6b7868", "team_a": "Bayern (3\u00d1\u00853)", "team_b": "Roma (3\u00d1\u00853)", "start_time": 1600827420.0, "url": "event/2371f474-d872-4623-9bc6-e580be6b7868", "team_a_image": null, "team_b_image": null, "match_country": "unknown", "league_name": "PRO Soccer League", "c": "0"}, {"id": "a05fee6a-1f76-4bbc-ba37-e1209f6c80bb", "team_a": "Barcelona (3\u0421\u20263)", "team_b": "Liverpool (3\u0421\u20263)", "start_time": 1600816620.0, "url": "event/a05fee6a-1f76-4bbc-ba37-e1209f6c80bb", "team_a_image": null, "team_b_image": null, "match_country": "unknown", "league_name": "PRO Soccer League", "c": "0"}, {"id": "dcfc62d3-2059-4bb9-8b3f-2a512c8c84e8", "team_a": "Bayern (3\u0421\u20263)", "team_b": "Roma (3\u0421\u20263)", "start_time": 1600816621.0, "url": "event/dcfc62d3-2059-4bb9-8b3f-2a512c8c84e8", "team_a_image": null, "team_b_image": null, "match_country": "unknown", "league_name": "PRO Soccer League", "c": "0"}]}, {"league_id": "78e95645-964b-4ba5-af12-6b6ac8e1c82d", "league_name": "Soap Soccer League", "league_country": "unknown", "matches": [{"id": "676d1249-d351-4a2e-a1ba-9f027a4baf47", "team_a": "Germany (SSL)", "team_b": "Spain (SSL)", "start_time": 1600815601.0, "url": "event/676d1249-d351-4a2e-a1ba-9f027a4baf47", "team_a_image": null, "team_b_image": null, "match_country": "unknown", "league_name": "Soap Soccer League", "c": "1"}]}, {"league_id": "a6dc183b-dcb8-4217-aa45-6da72f6b8657", "league_name": "Friendly Match", "league_country": "unknown", "matches": [{"id": "996ab9d2-c27c-4a0e-b9fe-807129821e65", "team_a": "California United", "team_b": "New York Cosmos", "start_time": 1600808400.0, "url": "event/996ab9d2-c27c-4a0e-b9fe-807129821e65", "team_a_image": null, "team_b_image": null, "match_country": "unknown", "league_name": "Friendly Match", "c": "1"}, {"id": "4006d67a-53df-4792-ad1c-835a8b58b132", "team_a": "Chattanooga", "team_b": "Los Angeles Force", "start_time": 1600819200.0, "url": "event/4006d67a-53df-4792-ad1c-835a8b58b132", "team_a_image": null, "team_b_image": null, "match_country": "unknown", "league_name": "Friendly Match", "c": "1"}]}, {"league_id": "0623c986-5b8e-4fb4-83d4-d3bd0a19d0fc", "league_name": "USA. USL", "league_country": "unknown", "matches": [{"id": "9cd23f2e-1302-4c23-a5ae-5618ad5a31c4", "team_a": "Austin Bold", "team_b": "Kansas City II", "start_time": 1600822800.0, "url": "event/9cd23f2e-1302-4c23-a5ae-5618ad5a31c4", "team_a_image": "https://cdn.livetv341.me/img/teams/fullsize/37708.gif", "team_b_image": "https://cdn.livetv341.me/img/teams/fullsize/39599.gif", "match_country": "unknown", "league_name": "USA. USL", "c": "1"}, {"id": "3732a2fb-a451-41da-a092-55e5dc196236", "team_a": "Hartford Athletic", "team_b": "Philadelphia II", "start_time": 1600902000.0, "url": "event/3732a2fb-a451-41da-a092-55e5dc196236", "team_a_image": "https://cdn.livetv341.me/img/teams/fullsize/37705.gif", "team_b_image": "https://cdn.livetv341.me/img/teams/fullsize/39591.gif", "match_country": "unknown", "league_name": "USA. USL", "c": "1"}, {"id": "2587908d-65eb-4e49-ba10-50ab1896edba", "team_a": "Charlotte Independence", "team_b": "Miami", "start_time": 1600902000.0, "url": "event/2587908d-65eb-4e49-ba10-50ab1896edba", "team_a_image": "https://cdn.livetv341.me/img/teams/fullsize/33693.gif", "team_b_image": "https://cdn.livetv341.me/img/teams/fullsize/22102.gif", "match_country": "unknown", "league_name": "USA. USL", "c": "1"}, {"id": "bad2ced7-99f4-4b98-afe6-9cf3a7bad358", "team_a": "Indy Eleven", "team_b": "Saint Louis FC", "start_time": 1600902000.0, "url": "event/bad2ced7-99f4-4b98-afe6-9cf3a7bad358", "team_a_image": "https://cdn.livetv341.me/img/teams/fullsize/33687.gif", "team_b_image": "https://cdn.livetv341.me/img/teams/fullsize/33706.gif", "match_country": "unknown", "league_name": "USA. USL", "c": "1"}, {"id": "d6bf7df0-6611-48f8-b092-180ee12b3afc", "team_a": "Atlanta United II", "team_b": "New York Red Bulls II", "start_time": 1600903800.0, "url": "event/d6bf7df0-6611-48f8-b092-180ee12b3afc", "team_a_image": "https://cdn.livetv341.me/img/teams/fullsize/39597.gif", "team_b_image": "https://cdn.livetv341.me/img/teams/fullsize/33688.gif", "match_country": "unknown", "league_name": "USA. USL", "c": "0"}]}, {"league_id": "72c171ae-0e27-4ba5-a771-c44d3ac8c489", "league_name": "AFC Champions League", "league_country": "unknown", "matches": [{"id": "fd7043ee-4277-4496-9e87-e9c07621be26", "team_a": "Al Wahda Abu Dhabi", "team_b": "Al Shorta Baghdad", "start_time": 1600873200.0, "url": "event/fd7043ee-4277-4496-9e87-e9c07621be26", "team_a_image": "https://cdn.livetv341.me/img/teams/fullsize/39758.gif", "team_b_image": "https://cdn.livetv341.me/img/teams/fullsize/44186.gif", "match_country": "unknown", "league_name": "AFC Champions League", "c": "1"}, {"id": "00842265-da1d-43bb-9503-5cf7f2d29d7c", "team_a": "Esteghlal", "team_b": "Al Ahli Jeddah", "start_time": 1600873200.0, "url": "event/00842265-da1d-43bb-9503-5cf7f2d29d7c", "team_a_image": "https://cdn.livetv341.me/img/teams/fullsize/33340.gif", "team_b_image": "https://cdn.livetv341.me/img/teams/fullsize/34074.gif", "match_country": "unknown", "league_name": "AFC Champions League", "c": "1"}, {"id": "32944e50-8b6a-4fe5-a364-18da85f855f8", "team_a": "Al Hilal", "team_b": "Shabab Al Ahli", "start_time": 1600884000.0, "url": "event/32944e50-8b6a-4fe5-a364-18da85f855f8", "team_a_image": "https://cdn.livetv341.me/img/teams/fullsize/34069.gif", "team_b_image": "https://cdn.livetv341.me/img/teams/fullsize/38275.gif", "match_country": "unknown", "league_name": "AFC Champions League", "c": "1"}, {"id": "2743c6bd-8e9d-4fff-9710-3ba0653d41b4", "team_a": "Shahr Khodrou", "team_b": "Pakhtakor", "start_time": 1600884000.0, "url": "event/2743c6bd-8e9d-4fff-9710-3ba0653d41b4", "team_a_image": "https://cdn.livetv341.me/img/teams/fullsize/42542.gif", "team_b_image": "https://cdn.livetv341.me/img/teams/fullsize/5643.gif", "match_country": "unknown", "league_name": "AFC Champions League", "c": "1"}]}, {"league_id": "df987f66-448c-4f30-869f-f046edf9ed65", "league_name": "Europa League Qualifying / \nThird Round.", "league_country": "unknown", "matches": [{"id": "58d0bfa8-701b-42ca-bb85-5a6457e38346", "team_a": "Apollon Limassol", "team_b": "Lech Poznan", "start_time": 1600876800.0, "url": "event/58d0bfa8-701b-42ca-bb85-5a6457e38346", "team_a_image": "https://cdn.livetv341.me/img/teams/fullsize/33582.gif", "team_b_image": "https://cdn.livetv341.me/img/teams/fullsize/32183.gif", "match_country": "unknown", "league_name": "Europa League Qualifying / \nThird Round.", "c": "1"}]}, {"league_id": "6981a683-b802-4c32-be2b-6b0b94b3ac1e", "league_name": "Champions League Qualifying / \nPlayoffs. First Match.", "league_country": "unknown", "matches": [{"id": "10ca7bb1-5a71-4583-a733-8461993784ae", "team_a": "Molde", "team_b": "Ferencvaros", "start_time": 1600887600.0, "url": "event/10ca7bb1-5a71-4583-a733-8461993784ae", "team_a_image": "https://cdn.livetv341.me/img/teams/fullsize/32265.gif", "team_b_image": "https://cdn.livetv341.me/img/teams/fullsize/34725.gif", "match_country": "unknown", "league_name": "Champions League Qualifying / \nPlayoffs. First Match.", "c": "1"}, {"id": "7402fd16-431d-489f-9365-43c46405ba8c", "team_a": "Gent", "team_b": "Dynamo Kiev", "start_time": 1600887600.0, "url": "event/7402fd16-431d-489f-9365-43c46405ba8c", "team_a_image": "https://cdn.livetv341.me/img/teams/fullsize/32684.gif", "team_b_image": "https://cdn.livetv341.me/img/teams/fullsize/32619.gif", "match_country": "unknown", "league_name": "Champions League Qualifying / \nPlayoffs. First Match.", "c": "1"}, {"id": "33076386-5779-4f17-9a71-5d4c06ad8da6", "team_a": "Olympiacos", "team_b": "Omonia", "start_time": 1600887600.0, "url": "event/33076386-5779-4f17-9a71-5d4c06ad8da6", "team_a_image": "https://cdn.livetv341.me/img/teams/fullsize/33012.gif", "team_b_image": "https://cdn.livetv341.me/img/teams/fullsize/33579.gif", "match_country": "unknown", "league_name": "Champions League Qualifying / \nPlayoffs. First Match.", "c": "1"}]}, {"league_id": "d83896c4-6f23-4ca5-9ed3-5e8d24d3a182", "league_name": "USA. MLS", "league_country": "unknown", "matches": [{"id": "32f2ceb1-d83d-41c1-b5ac-f21347a82d37", "team_a": "New England", "team_b": "Montreal", "start_time": 1600894800.0, "url": "event/32f2ceb1-d83d-41c1-b5ac-f21347a82d37", "team_a_image": "https://cdn.livetv341.me/img/teams/fullsize/32858.gif", "team_b_image": "https://cdn.livetv341.me/img/teams/fullsize/32857.gif", "match_country": "unknown", "league_name": "USA. MLS", "c": "1"}, {"id": "9e2094e0-a93d-424f-8d2e-867c2a30a8b7", "team_a": "New York City", "team_b": "Toronto", "start_time": 1600902000.0, "url": "event/9e2094e0-a93d-424f-8d2e-867c2a30a8b7", "team_a_image": "https://cdn.livetv341.me/img/teams/fullsize/32855.gif", "team_b_image": "https://cdn.livetv341.me/img/teams/fullsize/33929.gif", "match_country": "unknown", "league_name": "USA. MLS", "c": "1"}, {"id": "06d7703c-1890-4d49-998e-5256bc8e9e68", "team_a": "Atlanta United", "team_b": "Dallas", "start_time": 1600902000.0, "url": "event/06d7703c-1890-4d49-998e-5256bc8e9e68", "team_a_image": "https://cdn.livetv341.me/img/teams/fullsize/32851.gif", "team_b_image": "https://cdn.livetv341.me/img/teams/fullsize/32863.gif", "match_country": "unknown", "league_name": "USA. MLS", "c": "1"}, {"id": "5c20039a-d864-4148-89f0-da4dfcf70d55", "team_a": "Kansas City", "team_b": "Orlando City", "start_time": 1600903800.0, "url": "event/5c20039a-d864-4148-89f0-da4dfcf70d55", "team_a_image": "https://cdn.livetv341.me/img/teams/fullsize/32864.gif", "team_b_image": "https://cdn.livetv341.me/img/teams/fullsize/32859.gif", "match_country": "unknown", "league_name": "USA. MLS", "c": "0"}, {"id": "ef7d35d5-6418-4a9e-8d92-4e8137b1a471", "team_a": "Columbus", "team_b": "Minnesota", "start_time": 1600903800.0, "url": "event/ef7d35d5-6418-4a9e-8d92-4e8137b1a471", "team_a_image": "https://cdn.livetv341.me/img/teams/fullsize/32854.gif", "team_b_image": "https://cdn.livetv341.me/img/teams/fullsize/33180.gif", "match_country": "unknown", "league_name": "USA. MLS", "c": "0"}, {"id": "570243ba-5b61-4ac5-8355-4fc2f416b602", "team_a": "Cincinnati", "team_b": "Philadelphia", "start_time": 1600903800.0, "url": "event/570243ba-5b61-4ac5-8355-4fc2f416b602", "team_a_image": "https://cdn.livetv341.me/img/teams/fullsize/39624.gif", "team_b_image": "https://cdn.livetv341.me/img/teams/fullsize/33928.gif", "match_country": "unknown", "league_name": "USA. MLS", "c": "0"}, {"id": "6eb5af5b-9350-47ab-9647-eecd7a549736", "team_a": "Chicago", "team_b": "Houston Dynamo", "start_time": 1600903800.0, "url": "event/6eb5af5b-9350-47ab-9647-eecd7a549736", "team_a_image": "https://cdn.livetv341.me/img/teams/fullsize/39325.gif", "team_b_image": "https://cdn.livetv341.me/img/teams/fullsize/32872.gif", "match_country": "unknown", "league_name": "USA. MLS", "c": "0"}]}, {"league_id": "c2492468-3974-4d5e-9bd1-d78ec1471375", "league_name": "USA. USL League One", "league_country": "unknown", "matches": [{"id": "9faa172e-2fb5-4b26-a3c0-9dc3468ebd63", "team_a": "Richmond Kickers", "team_b": "Fort Lauderdale", "start_time": 1600900200.0, "url": "event/9faa172e-2fb5-4b26-a3c0-9dc3468ebd63", "team_a_image": "https://cdn.livetv341.me/img/teams/fullsize/33695.gif", "team_b_image": "https://cdn.livetv341.me/img/teams/fullsize/12811.gif", "match_country": "unknown", "league_name": "USA. USL League One", "c": "1"}]}]