[{"league_id": "5c43a918-dac1-4398-8b2a-16566ed231ee", "league_name": "Bundesliga", "league_country": "germany", "matches": [{"id": "e4c46eec-b23e-4e48-9f6a-ffdb18783097", "team_a": "Werder", "team_b": "Leverkusen", "start_time": 1589826600.0, "url": "event/e4c46eec-b23e-4e48-9f6a-ffdb18783097", "team_a_image": "https://cdn.livetv301.me/img/teams/fullsize/32145.gif", "team_b_image": "https://cdn.livetv301.me/img/teams/fullsize/32130.gif", "match_country": "germany", "league_name": "Germany. Bundesliga", "c": "1"}]}, {"league_id": "8b24341f-ccf3-4e15-af1a-46cfab655dae", "league_name": "FIFA. Elite League", "league_country": "unknown", "matches": [{"id": "cf206b62-4ced-47f3-b4b8-c9b00f2dc9f6", "team_a": "Tottenham Hotspur", "team_b": "Benfica", "start_time": "LIVE", "url": "event/cf206b62-4ced-47f3-b4b8-c9b00f2dc9f6", "team_a_image": null, "team_b_image": null, "match_country": "unknown", "league_name": "FIFA. Elite League", "c": "0"}]}, {"league_id": "edcd463a-aa74-4b05-bbea-a4f6ae84684d", "league_name": "Soap Soccer League. Women", "league_country": "unknown", "matches": [{"id": "fc4b29d2-89e9-48c5-a6b9-ae2d8c37816d", "team_a": "England (Amateur) Women", "team_b": "Russia (Amateur) Women", "start_time": "LIVE", "url": "event/fc4b29d2-89e9-48c5-a6b9-ae2d8c37816d", "team_a_image": null, "team_b_image": null, "match_country": "unknown", "league_name": "Soap Soccer League. Women", "c": "0"}]}, {"league_id": "cff9a2ee-29df-4c64-8b06-a581cb8483b2", "league_name": "Short Football 2x2", "league_country": "unknown", "matches": [{"id": "9c6697c6-5e02-43f8-8ebb-a323fc8a61d0", "team_a": "Barcelona+", "team_b": "Ajax+", "start_time": "LIVE", "url": "event/9c6697c6-5e02-43f8-8ebb-a323fc8a61d0", "team_a_image": null, "team_b_image": null, "match_country": "unknown", "league_name": "Short Football 2x2", "c": "0"}]}, {"league_id": "ab5fdeea-4fda-4045-ade0-380ee420c7bf", "league_name": "FIFA 20. Electronic Cyber Champions League", "league_country": "unknown", "matches": [{"id": "cc73357d-5231-4b4e-8ab2-5477a3b01419", "team_a": "Bayer 04 Leverkusen (fleshka77)", "team_b": "Chelsea (Fric)", "start_time": "LIVE", "url": "event/cc73357d-5231-4b4e-8ab2-5477a3b01419", "team_a_image": null, "team_b_image": null, "match_country": "unknown", "league_name": "FIFA 20. Electronic Cyber Champions League", "c": "0"}]}, {"league_id": "5f60913f-4de9-4983-a293-b370c3cd1847", "league_name": "FIFA. LigaPro", "league_country": "unknown", "matches": [{"id": "aa6c7b26-052b-47e4-bce1-29a6abfb4f66", "team_a": "Kazan (RUB)", "team_b": "Tundra (TES)", "start_time": 1589796600.0, "url": "event/aa6c7b26-052b-47e4-bce1-29a6abfb4f66", "team_a_image": null, "team_b_image": null, "match_country": "unknown", "league_name": "FIFA. LigaPro", "c": "1"}]}]