[{"league_id": "3b8fc593-4629-4413-8d8a-e8941dc9c290", "league_name": "Championship", "league_country": "england", "matches": [{"id": "b037703e-b112-491f-bf6f-12ff528db370", "team_a": "Swansea City", "team_b": "Brentford", "start_time": 1595784600.0, "url": "event/b037703e-b112-491f-bf6f-12ff528db370", "team_a_image": "https://cdn.livetv323.me/img/teams/fullsize/20534.gif", "team_b_image": "https://cdn.livetv323.me/img/teams/fullsize/29249.gif", "match_country": "england", "league_name": "England. Championship", "c": "0"}]}, {"league_id": "0b0d4948-4e86-4f7c-9512-59c7276515fc", "league_name": "Premier League", "league_country": "england", "matches": [{"id": "f513f780-8669-4081-8cd6-ab046dd513a5", "team_a": "West Ham", "team_b": "Aston Villa", "start_time": "LIVE", "url": "event/f513f780-8669-4081-8cd6-ab046dd513a5", "team_a_image": "https://cdn.livetv323.me/img/teams/fullsize/32110.gif", "team_b_image": "https://cdn.livetv323.me/img/teams/fullsize/154.gif", "match_country": "england", "league_name": "Premier League", "c": "0"}, {"id": "729f1b73-ce1a-4129-861d-8888d260c5f0", "team_a": "Southampton", "team_b": "Sheffield Utd", "start_time": "LIVE", "url": "event/729f1b73-ce1a-4129-861d-8888d260c5f0", "team_a_image": "https://cdn.livetv323.me/img/teams/fullsize/32107.gif", "team_b_image": "https://cdn.livetv323.me/img/teams/fullsize/9744.gif", "match_country": "england", "league_name": "Premier League", "c": "0"}, {"id": "7123275a-b7bb-4fe4-a962-b3ef63fc10cf", "team_a": "Newcastle", "team_b": "Liverpool", "start_time": "LIVE", "url": "event/7123275a-b7bb-4fe4-a962-b3ef63fc10cf", "team_a_image": "https://cdn.livetv323.me/img/teams/fullsize/32106.gif", "team_b_image": "https://cdn.livetv323.me/img/teams/fullsize/32103.gif", "match_country": "england", "league_name": "Premier League", "c": "0"}, {"id": "8cf612c8-0c13-422f-8c62-88913cb817c6", "team_a": "Manchester City", "team_b": "Norwich", "start_time": "LIVE", "url": "event/8cf612c8-0c13-422f-8c62-88913cb817c6", "team_a_image": "https://cdn.livetv323.me/img/teams/fullsize/33185.gif", "team_b_image": "https://cdn.livetv323.me/img/teams/fullsize/10249.gif", "match_country": "england", "league_name": "Premier League", "c": "0"}, {"id": "47d0d9b7-ffc8-4071-8ff6-f0a29fe7bc7b", "team_a": "Leicester City", "team_b": "Manchester Utd", "start_time": "LIVE", "url": "event/47d0d9b7-ffc8-4071-8ff6-f0a29fe7bc7b", "team_a_image": "https://cdn.livetv323.me/img/teams/fullsize/32102.gif", "team_b_image": "https://cdn.livetv323.me/img/teams/fullsize/32105.gif", "match_country": "england", "league_name": "Premier League", "c": "0"}, {"id": "44661cc8-1831-40a5-b79d-30829abf5250", "team_a": "Everton", "team_b": "Bournemouth", "start_time": "LIVE", "url": "event/44661cc8-1831-40a5-b79d-30829abf5250", "team_a_image": "https://cdn.livetv323.me/img/teams/fullsize/32099.gif", "team_b_image": "https://cdn.livetv323.me/img/teams/fullsize/32094.gif", "match_country": "england", "league_name": "Premier League", "c": "0"}, {"id": "2d0f168b-5b23-425f-96fd-676ceb6fc0b1", "team_a": "Crystal Palace", "team_b": "Tottenham", "start_time": "LIVE", "url": "event/2d0f168b-5b23-425f-96fd-676ceb6fc0b1", "team_a_image": "https://cdn.livetv323.me/img/teams/fullsize/32098.gif", "team_b_image": "https://cdn.livetv323.me/img/teams/fullsize/34195.gif", "match_country": "england", "league_name": "Premier League", "c": "0"}, {"id": "e8bb6e37-8bad-44ce-81d5-f1ea2e911629", "team_a": "Chelsea", "team_b": "Wolverhampton", "start_time": "LIVE", "url": "event/e8bb6e37-8bad-44ce-81d5-f1ea2e911629", "team_a_image": "https://cdn.livetv323.me/img/teams/fullsize/32097.gif", "team_b_image": "https://cdn.livetv323.me/img/teams/fullsize/32111.gif", "match_country": "england", "league_name": "Premier League", "c": "0"}, {"id": "dd70671d-68ff-4d20-b216-7b35803e30e4", "team_a": "Burnley", "team_b": "Brighton & Hove Albion", "start_time": "LIVE", "url": "event/dd70671d-68ff-4d20-b216-7b35803e30e4", "team_a_image": "https://cdn.livetv323.me/img/teams/fullsize/32047.gif", "team_b_image": "https://cdn.livetv323.me/img/teams/fullsize/32095.gif", "match_country": "england", "league_name": "Premier League", "c": "1"}, {"id": "ae318f6f-4950-4ed2-8fb6-5acd23afa0c5", "team_a": "Arsenal", "team_b": "Watford", "start_time": "LIVE", "url": "event/ae318f6f-4950-4ed2-8fb6-5acd23afa0c5", "team_a_image": "https://cdn.livetv323.me/img/teams/fullsize/32015.gif", "team_b_image": "https://cdn.livetv323.me/img/teams/fullsize/32109.gif", "match_country": "england", "league_name": "Premier League", "c": "1"}]}, {"league_id": "6edf95ac-de5f-481a-9aa0-b7cc39e247b7", "league_name": "Serie A", "league_country": "italy", "matches": [{"id": "a5b21b55-f591-4923-8902-984a6e5f9eb0", "team_a": "Bologna", "team_b": "Lecce", "start_time": "LIVE", "url": "event/a5b21b55-f591-4923-8902-984a6e5f9eb0", "team_a_image": "https://cdn.livetv323.me/img/teams/fullsize/37947.gif", "team_b_image": "https://cdn.livetv323.me/img/teams/fullsize/4933.gif", "match_country": "italy", "league_name": "Serie A", "c": "1"}, {"id": "e7c0b53a-58ca-4420-9767-30763cd66ab5", "team_a": "Roma", "team_b": "Fiorentina", "start_time": 1595784600.0, "url": "event/e7c0b53a-58ca-4420-9767-30763cd66ab5", "team_a_image": "https://cdn.livetv323.me/img/teams/fullsize/32149.gif", "team_b_image": "https://cdn.livetv323.me/img/teams/fullsize/39400.gif", "match_country": "italy", "league_name": "Italy. Serie A", "c": "1"}, {"id": "d1660af7-f755-48fb-917b-468fd169ab14", "team_a": "Hellas Verona", "team_b": "Lazio", "start_time": 1595784600.0, "url": "event/d1660af7-f755-48fb-917b-468fd169ab14", "team_a_image": "https://cdn.livetv323.me/img/teams/fullsize/32165.gif", "team_b_image": "https://cdn.livetv323.me/img/teams/fullsize/37949.gif", "match_country": "italy", "league_name": "Italy. Serie A", "c": "0"}, {"id": "83cdf68a-81d0-4cd7-ab6f-6cf92bae9b6d", "team_a": "SPAL", "team_b": "Torino", "start_time": 1595784600.0, "url": "event/83cdf68a-81d0-4cd7-ab6f-6cf92bae9b6d", "team_a_image": "https://cdn.livetv323.me/img/teams/fullsize/37951.gif", "team_b_image": "https://cdn.livetv323.me/img/teams/fullsize/32155.gif", "match_country": "italy", "league_name": "Italy. Serie A", "c": "1"}, {"id": "9aa819d7-b6ed-4280-a693-6e0d05b78e72", "team_a": "Cagliari", "team_b": "Udinese", "start_time": 1595784600.0, "url": "event/9aa819d7-b6ed-4280-a693-6e0d05b78e72", "team_a_image": "https://cdn.livetv323.me/img/teams/fullsize/33205.gif", "team_b_image": "https://cdn.livetv323.me/img/teams/fullsize/33201.gif", "match_country": "italy", "league_name": "Italy. Serie A", "c": "1"}, {"id": "7d812bca-65b0-49c2-a74d-b51832c18927", "team_a": "Juventus", "team_b": "Sampdoria", "start_time": 1595792700.0, "url": "event/7d812bca-65b0-49c2-a74d-b51832c18927", "team_a_image": "https://cdn.livetv323.me/img/teams/fullsize/32147.gif", "team_b_image": "https://cdn.livetv323.me/img/teams/fullsize/32156.gif", "match_country": "italy", "league_name": "Italy. Serie A", "c": "1"}]}, {"league_id": "1634c739-9f49-4ff5-85d6-edaee03f29da", "league_name": "Sweden. Allsvenskan", "league_country": "sweden", "matches": [{"id": "48e32fa2-1ddd-43ed-b883-0034ff1f955a", "team_a": "AIK", "team_b": "Djurgardens", "start_time": "LIVE", "url": "event/48e32fa2-1ddd-43ed-b883-0034ff1f955a", "team_a_image": "https://cdn.livetv323.me/img/teams/fullsize/32417.gif", "team_b_image": "https://cdn.livetv323.me/img/teams/fullsize/32948.gif", "match_country": "sweden", "league_name": "Sweden. Allsvenskan", "c": "1"}, {"id": "51bf31ac-8e09-49d8-a61f-135b9a87ceb1", "team_a": "Sirius", "team_b": "Malmo", "start_time": "LIVE", "url": "event/51bf31ac-8e09-49d8-a61f-135b9a87ceb1", "team_a_image": "https://cdn.livetv323.me/img/teams/fullsize/32428.gif", "team_b_image": "https://cdn.livetv323.me/img/teams/fullsize/32421.gif", "match_country": "sweden", "league_name": "Sweden. Allsvenskan", "c": "1"}]}, {"league_id": "97e2bf49-18ce-49f6-b2e2-672b30634683", "league_name": "Turkey. 1. Lig / \nSemifinal.", "league_country": "turkey", "matches": [{"id": "f66c6914-3f0f-4d1e-85e8-4435944c2a11", "team_a": "Adana Demirspor", "team_b": "Bursaspor", "start_time": 1595786400.0, "url": "event/f66c6914-3f0f-4d1e-85e8-4435944c2a11", "team_a_image": "https://cdn.livetv323.me/img/teams/fullsize/13027.gif", "team_b_image": "https://cdn.livetv323.me/img/teams/fullsize/32487.gif", "match_country": "turkey", "league_name": "Turkey. 1. Lig / \nSemifinal.", "c": "1"}, {"id": "22904e89-56a5-4aae-9aa4-eca4926d8ef4", "team_a": "Akhisar", "team_b": "Fatih Karagumruk", "start_time": 1595786400.0, "url": "event/22904e89-56a5-4aae-9aa4-eca4926d8ef4", "team_a_image": "https://cdn.livetv323.me/img/teams/fullsize/32485.gif", "team_b_image": "https://cdn.livetv323.me/img/teams/fullsize/26483.gif", "match_country": "turkey", "league_name": "Turkey. 1. Lig / \nSemifinal.", "c": "1"}]}, {"league_id": "be998325-7757-40db-80b1-399c90b687a5", "league_name": "Turkey. 1. Lig", "league_country": "turkey", "matches": [{"id": "dfafb55c-fe27-4823-ab73-5a175d36d842", "team_a": "Akhisar Belediyespor", "team_b": "Fatih Karagumruk", "start_time": 1595786400.0, "url": "event/dfafb55c-fe27-4823-ab73-5a175d36d842", "team_a_image": null, "team_b_image": null, "match_country": "turkey", "league_name": "Turkey. PTT 1. Lig", "c": "1"}, {"id": "f66c6914-3f0f-4d1e-85e8-4435944c2a11", "team_a": "Adana Demirspor", "team_b": "Bursaspor", "start_time": 1595786400.0, "url": "event/f66c6914-3f0f-4d1e-85e8-4435944c2a11", "team_a_image": null, "team_b_image": null, "match_country": "turkey", "league_name": "Turkey. PTT 1. Lig", "c": "1"}]}, {"league_id": "e5eb5331-1a7b-4ef0-ba32-5a254f70fc58", "league_name": "Turkey. Super Lig", "league_country": "turkey", "matches": [{"id": "b67c114a-bebc-46f7-8927-ea321e36b6f8", "team_a": "Kasimpasa", "team_b": "Istanbul BB", "start_time": "LIVE", "url": "event/b67c114a-bebc-46f7-8927-ea321e36b6f8", "team_a_image": "https://cdn.livetv323.me/img/teams/fullsize/32483.gif", "team_b_image": "https://cdn.livetv323.me/img/teams/fullsize/33020.gif", "match_country": "turkey", "league_name": "Turkey. Super Lig", "c": "0"}]}, {"league_id": "13b85ba2-12af-4aec-8359-81d9937e3d02", "league_name": "Brazil. Campeonato Gaucho", "league_country": "brazil", "matches": [{"id": "fe7f2ef0-5229-44d3-978c-6d4446574034", "team_a": "Gremio Brasil", "team_b": "Juventude", "start_time": 1595790000.0, "url": "event/fe7f2ef0-5229-44d3-978c-6d4446574034", "team_a_image": "https://cdn.livetv323.me/img/teams/fullsize/32692.gif", "team_b_image": "https://cdn.livetv323.me/img/teams/fullsize/22288.gif", "match_country": "brazil", "league_name": "Brazil. Campeonato Gaucho", "c": "0"}, {"id": "acaf0d0b-7c7f-45a6-8469-6ad1159c08d1", "team_a": "Caxias do Sul", "team_b": "Pelotas", "start_time": 1595790000.0, "url": "event/acaf0d0b-7c7f-45a6-8469-6ad1159c08d1", "team_a_image": "https://cdn.livetv323.me/img/teams/fullsize/8178.gif", "team_b_image": "https://cdn.livetv323.me/img/teams/fullsize/39553.gif", "match_country": "brazil", "league_name": "Brazil. Campeonato Gaucho", "c": "1"}, {"id": "0741bea2-d956-4ca7-9b23-dfbc459876b7", "team_a": "Aimore", "team_b": "Sao Luiz", "start_time": 1595800800.0, "url": "event/0741bea2-d956-4ca7-9b23-dfbc459876b7", "team_a_image": "https://cdn.livetv323.me/img/teams/fullsize/24970.gif", "team_b_image": "https://cdn.livetv323.me/img/teams/fullsize/31323.gif", "match_country": "brazil", "league_name": "Brazil. Campeonato Gaucho", "c": "1"}, {"id": "20a60318-7c0f-4919-81f8-7bcf174b7c95", "team_a": "Sao-Jose-RS", "team_b": "Novo-Hamburgo", "start_time": 1595800800.0, "url": "event/20a60318-7c0f-4919-81f8-7bcf174b7c95", "team_a_image": "https://cdn.livetv323.me/img/teams/fullsize/26334.gif", "team_b_image": "https://cdn.livetv323.me/img/teams/fullsize/24969.gif", "match_country": "brazil", "league_name": "Brazil. Campeonato Gaucho", "c": "1"}]}, {"league_id": "43444ba3-4e2a-4d0e-ab80-e875d2177eb9", "league_name": "Brazil. Campeonato Paulista", "league_country": "brazil", "matches": [{"id": "a0ac0bbf-db15-4d2c-bb1e-2fd7745bf826", "team_a": "Bragantino", "team_b": "Botafogo SP", "start_time": 1595790000.0, "url": "event/a0ac0bbf-db15-4d2c-bb1e-2fd7745bf826", "team_a_image": "https://cdn.livetv323.me/img/teams/fullsize/41376.gif", "team_b_image": "https://cdn.livetv323.me/img/teams/fullsize/11152.gif", "match_country": "brazil", "league_name": "Brazil. Campeonato Paulista", "c": "1"}, {"id": "3f246875-7fc5-4def-a788-24159ebdc82f", "team_a": "Ferroviarios", "team_b": "Inter de Limeira", "start_time": 1595790000.0, "url": "event/3f246875-7fc5-4def-a788-24159ebdc82f", "team_a_image": "https://cdn.livetv323.me/img/teams/fullsize/37456.gif", "team_b_image": "https://cdn.livetv323.me/img/teams/fullsize/28276.gif", "match_country": "brazil", "league_name": "Brazil. Campeonato Paulista", "c": "1"}, {"id": "f411d2f7-56a8-4797-a067-010d8e1afca0", "team_a": "Guarani", "team_b": "Sao Paolo", "start_time": 1595790000.0, "url": "event/f411d2f7-56a8-4797-a067-010d8e1afca0", "team_a_image": "https://cdn.livetv323.me/img/teams/fullsize/29239.gif", "team_b_image": "https://cdn.livetv323.me/img/teams/fullsize/32689.gif", "match_country": "brazil", "league_name": "Brazil. Campeonato Paulista", "c": "1"}, {"id": "87a22186-521b-4214-a9e6-a021d6fd6127", "team_a": "Mirassol", "team_b": "Ponte Preta", "start_time": 1595790000.0, "url": "event/87a22186-521b-4214-a9e6-a021d6fd6127", "team_a_image": "https://cdn.livetv323.me/img/teams/fullsize/39683.gif", "team_b_image": "https://cdn.livetv323.me/img/teams/fullsize/11195.gif", "match_country": "brazil", "league_name": "Brazil. Campeonato Paulista", "c": "1"}, {"id": "4e5d0c7c-ec0b-4317-bf5d-1b3d7626e9a6", "team_a": "Novorizontino", "team_b": "Santos", "start_time": 1595790000.0, "url": "event/4e5d0c7c-ec0b-4317-bf5d-1b3d7626e9a6", "team_a_image": "https://cdn.livetv323.me/img/teams/fullsize/21366.gif", "team_b_image": "https://cdn.livetv323.me/img/teams/fullsize/32703.gif", "match_country": "brazil", "league_name": "Brazil. Campeonato Paulista", "c": "1"}, {"id": "fcc6a317-df72-4875-9542-fadaf6513b84", "team_a": "Oeste", "team_b": "Corinthians", "start_time": 1595790000.0, "url": "event/fcc6a317-df72-4875-9542-fadaf6513b84", "team_a_image": "https://cdn.livetv323.me/img/teams/fullsize/11158.gif", "team_b_image": "https://cdn.livetv323.me/img/teams/fullsize/32695.gif", "match_country": "brazil", "league_name": "Brazil. Campeonato Paulista", "c": "1"}, {"id": "b79840d1-f478-4628-850f-ff22d23c28b0", "team_a": "Palmeiras", "team_b": "Agua Santa", "start_time": 1595790000.0, "url": "event/b79840d1-f478-4628-850f-ff22d23c28b0", "team_a_image": "https://cdn.livetv323.me/img/teams/fullsize/32694.gif", "team_b_image": "https://cdn.livetv323.me/img/teams/fullsize/21368.gif", "match_country": "brazil", "league_name": "Brazil. Campeonato Paulista", "c": "1"}, {"id": "7536df4f-159e-43eb-87da-69d02de15d37", "team_a": "Santo Andre", "team_b": "Ituano", "start_time": 1595790000.0, "url": "event/7536df4f-159e-43eb-87da-69d02de15d37", "team_a_image": "https://cdn.livetv323.me/img/teams/fullsize/5698.gif", "team_b_image": "https://cdn.livetv323.me/img/teams/fullsize/11154.gif", "match_country": "brazil", "league_name": "Brazil. Campeonato Paulista", "c": "1"}]}, {"league_id": "f6cbb7a1-bab0-4910-bc66-fb9a5b731f0a", "league_name": "Brazil. Campeonato Pernambucano / \nSemifinal.", "league_country": "brazil", "matches": [{"id": "fe695345-3135-477b-9bc5-b214f226fbad", "team_a": "Nautico", "team_b": "Central", "start_time": 1595790000.0, "url": "event/fe695345-3135-477b-9bc5-b214f226fbad", "team_a_image": "https://cdn.livetv323.me/img/teams/fullsize/10877.gif", "team_b_image": "https://cdn.livetv323.me/img/teams/fullsize/28139.gif", "match_country": "brazil", "league_name": "Brazil. Campeonato Pernambucano / \nSemifinal.", "c": "1"}]}, {"league_id": "787bd262-dde8-4dde-a5de-662c6e14d90e", "league_name": "Brazil. Campeonato Pernambucano / \nMen. Semifinal.", "league_country": "brazil", "matches": [{"id": "62952a08-3a2b-4a81-b9d7-c7a505a16434", "team_a": "Retro", "team_b": "Afogadus", "start_time": 1595804400.0, "url": "event/62952a08-3a2b-4a81-b9d7-c7a505a16434", "team_a_image": "https://cdn.livetv323.me/img/teams/fullsize/42775.gif", "team_b_image": "https://cdn.livetv323.me/img/teams/fullsize/30693.gif", "match_country": "brazil", "league_name": "Brazil. Campeonato Pernambucano / \nMen. Semifinal.", "c": "1"}]}, {"league_id": "8104390b-bcdd-43a1-8e5e-617441d94487", "league_name": "Superliga", "league_country": "denmark", "matches": [{"id": "fa9bd6a8-0e30-432e-9380-2d67704f057f", "team_a": "Midtjylland", "team_b": "Aalborg BK", "start_time": 1595782800.0, "url": "event/fa9bd6a8-0e30-432e-9380-2d67704f057f", "team_a_image": "https://cdn.livetv323.me/img/teams/fullsize/37932.gif", "team_b_image": "https://cdn.livetv323.me/img/teams/fullsize/32497.gif", "match_country": "denmark", "league_name": "Denmark. Superliga", "c": "0"}, {"id": "7fa80d28-44f9-456b-9117-b420018cd993", "team_a": "Copenhagen", "team_b": "Nordsjaelland", "start_time": 1595782800.0, "url": "event/7fa80d28-44f9-456b-9117-b420018cd993", "team_a_image": "https://cdn.livetv323.me/img/teams/fullsize/32494.gif", "team_b_image": "https://cdn.livetv323.me/img/teams/fullsize/41345.gif", "match_country": "denmark", "league_name": "Denmark. Superliga", "c": "0"}, {"id": "eb0b9dc6-4b3c-4f2a-8ed6-50b35327c98b", "team_a": "AGF Aarhus", "team_b": "Brondby", "start_time": 1595782800.0, "url": "event/eb0b9dc6-4b3c-4f2a-8ed6-50b35327c98b", "team_a_image": "https://cdn.livetv323.me/img/teams/fullsize/32496.gif", "team_b_image": "https://cdn.livetv323.me/img/teams/fullsize/32493.gif", "match_country": "denmark", "league_name": "Denmark. Superliga", "c": "0"}]}, {"league_id": "35c4f68a-e392-4e62-a6a8-65e362f04241", "league_name": "Mexico. Liga MX", "league_country": "mexico", "matches": [{"id": "893ad604-aba8-4b0b-9b1f-e856e1323edc", "team_a": "UNAM", "team_b": "Queretaro", "start_time": 1595782800.0, "url": "event/893ad604-aba8-4b0b-9b1f-e856e1323edc", "team_a_image": "https://cdn.livetv323.me/img/teams/fullsize/32769.gif", "team_b_image": "https://cdn.livetv323.me/img/teams/fullsize/32777.gif", "match_country": "mexico", "league_name": "Mexico. Liga MX", "c": "1"}, {"id": "30f33bf3-7795-4400-9c92-1977ebe16b30", "team_a": "Monterrey", "team_b": "Toluca", "start_time": 1595808000.0, "url": "event/30f33bf3-7795-4400-9c92-1977ebe16b30", "team_a_image": "https://cdn.livetv323.me/img/teams/fullsize/32771.gif", "team_b_image": "https://cdn.livetv323.me/img/teams/fullsize/32894.gif", "match_country": "mexico", "league_name": "Mexico. Liga MX", "c": "1"}]}, {"league_id": "1420cd70-9d2d-4c50-b6aa-8d1a2866830a", "league_name": "Primeira Liga", "league_country": "portugal", "matches": [{"id": "27c4e280-4b60-4c15-92b9-e20622d83c13", "team_a": "Portimonense", "team_b": "Aves", "start_time": 1595788200.0, "url": "event/27c4e280-4b60-4c15-92b9-e20622d83c13", "team_a_image": "https://cdn.livetv323.me/img/teams/fullsize/32242.gif", "team_b_image": "https://cdn.livetv323.me/img/teams/fullsize/32237.gif", "match_country": "portugal", "league_name": "Portugal. Primeira Liga", "c": "1"}, {"id": "63ec424f-2ff9-4b34-bd37-b312d401e830", "team_a": "Vitoria Setubal", "team_b": "Os Belenenses", "start_time": 1595788200.0, "url": "event/63ec424f-2ff9-4b34-bd37-b312d401e830", "team_a_image": "https://cdn.livetv323.me/img/teams/fullsize/32250.gif", "team_b_image": "https://cdn.livetv323.me/img/teams/fullsize/38067.gif", "match_country": "portugal", "league_name": "Portugal. Primeira Liga", "c": "0"}, {"id": "5724c572-1750-41cf-aceb-e39d21560e96", "team_a": "Moreirense", "team_b": "Tondela", "start_time": 1595788200.0, "url": "event/5724c572-1750-41cf-aceb-e39d21560e96", "team_a_image": "https://cdn.livetv323.me/img/teams/fullsize/32240.gif", "team_b_image": "https://cdn.livetv323.me/img/teams/fullsize/32628.gif", "match_country": "portugal", "league_name": "Portugal. Primeira Liga", "c": "1"}]}, {"league_id": "6ca52ea6-a78f-4d8e-8344-3096e559f886", "league_name": "Belarus Championship. ALF. Major League", "league_country": "belarus", "matches": [{"id": "12081556-74d0-443b-bf37-395a638f6838", "team_a": "Urozhaynaya", "team_b": "Alpha Minsk", "start_time": "LIVE", "url": "event/12081556-74d0-443b-bf37-395a638f6838", "team_a_image": null, "team_b_image": null, "match_country": "belarus", "league_name": "Belarus Championship. ALF. Major League", "c": "0"}]}, {"league_id": "739d99d0-3461-4036-924f-31b32a32940b", "league_name": "Belarus Premier League", "league_country": "belarus", "matches": [{"id": "5d4c6da2-a197-4ef2-a4e7-8e367b3ca896", "team_a": "BATE", "team_b": "Minsk", "start_time": "LIVE", "url": "event/5d4c6da2-a197-4ef2-a4e7-8e367b3ca896", "team_a_image": "https://cdn.livetv323.me/img/teams/fullsize/40880.gif", "team_b_image": "https://cdn.livetv323.me/img/teams/fullsize/32891.gif", "match_country": "belarus", "league_name": "Belarus. Premier League", "c": "0"}, {"id": "9d5fd938-e39c-48d5-b2df-4ac7dad4f658", "team_a": "Shakhtyor Sl", "team_b": "Smolevichi", "start_time": 1595782800.0, "url": "event/9d5fd938-e39c-48d5-b2df-4ac7dad4f658", "team_a_image": "https://cdn.livetv323.me/img/teams/fullsize/32762.gif", "team_b_image": "https://cdn.livetv323.me/img/teams/fullsize/41391.gif", "match_country": "belarus", "league_name": "Belarus. Premier League", "c": "0"}]}, {"league_id": "51bd3a85-028e-45cd-add1-cb023ad76351", "league_name": "Belarus. Premier League. Women", "league_country": "belarus", "matches": [{"id": "e21168cb-fe2b-412c-bb97-34813a0abff2", "team_a": "Minsk (Women)", "team_b": "Bobruichanka Bobruisk (Women)", "start_time": 1595782800.0, "url": "event/e21168cb-fe2b-412c-bb97-34813a0abff2", "team_a_image": null, "team_b_image": null, "match_country": "belarus", "league_name": "Belarus. Premier League. Women", "c": "1"}]}, {"league_id": "a523c3ab-c290-4bb9-8de6-01b41f7374d3", "league_name": "Finland. Veikkausliiga", "league_country": "finland", "matches": [{"id": "64d09548-36ca-4978-8ccf-5b040d6fa571", "team_a": "Honka", "team_b": "RoPS", "start_time": "LIVE", "url": "event/64d09548-36ca-4978-8ccf-5b040d6fa571", "team_a_image": "https://cdn.livetv323.me/img/teams/fullsize/33161.gif", "team_b_image": "https://cdn.livetv323.me/img/teams/fullsize/32826.gif", "match_country": "finland", "league_name": "Finland. Veikkausliiga", "c": "1"}, {"id": "73a665f7-0bb1-46bd-8e81-89b6869dcfdb", "team_a": "Kuopion Palloseura", "team_b": "Seinajoen Jalkapallokerho", "start_time": "LIVE", "url": "event/73a665f7-0bb1-46bd-8e81-89b6869dcfdb", "team_a_image": null, "team_b_image": null, "match_country": "finland", "league_name": "Finland. Veikkausliiga", "c": "0"}, {"id": "5f275d2b-82cf-4dc7-8e5b-9d8de8a6f4dc", "team_a": "Mariehamn", "team_b": "HIFK", "start_time": "LIVE", "url": "event/5f275d2b-82cf-4dc7-8e5b-9d8de8a6f4dc", "team_a_image": "https://cdn.livetv323.me/img/teams/fullsize/32831.gif", "team_b_image": "https://cdn.livetv323.me/img/teams/fullsize/17594.gif", "match_country": "finland", "league_name": "Finland. Veikkausliiga", "c": "1"}, {"id": "a2e89e6b-0050-4ae1-a898-331becd575b0", "team_a": "Haka", "team_b": "Inter Turku", "start_time": "LIVE", "url": "event/a2e89e6b-0050-4ae1-a898-331becd575b0", "team_a_image": "https://cdn.livetv323.me/img/teams/fullsize/17593.gif", "team_b_image": "https://cdn.livetv323.me/img/teams/fullsize/32829.gif", "match_country": "finland", "league_name": "Finland. Veikkausliiga", "c": "0"}, {"id": "04ebe202-62cf-4b2b-8712-7b14384d8f9d", "team_a": "KuPS Kuopio", "team_b": "SJK", "start_time": 1595777400.0, "url": "event/04ebe202-62cf-4b2b-8712-7b14384d8f9d", "team_a_image": "https://cdn.livetv323.me/img/teams/fullsize/32827.gif", "team_b_image": "https://cdn.livetv323.me/img/teams/fullsize/32830.gif", "match_country": "finland", "league_name": "Finland. Veikkausliiga", "c": "1"}]}, {"league_id": "3a1671b6-a590-4f83-95ab-5e624e156aa7", "league_name": "Georgia. League 2", "league_country": "georgia", "matches": [{"id": "b3ffe62f-41c3-42fc-8d2f-47e1a87e365e", "team_a": "Merani Martvili", "team_b": "Metalurgi Rustavi", "start_time": 1595781900.0, "url": "event/b3ffe62f-41c3-42fc-8d2f-47e1a87e365e", "team_a_image": null, "team_b_image": null, "match_country": "georgia", "league_name": "Georgia. League 2", "c": "1"}]}, {"league_id": "14714ed8-0010-456c-8554-b3a7ecd6f089", "league_name": "Georgia. Erovnuli Liga", "league_country": "georgia", "matches": [{"id": "a4b1f902-2765-4699-8a0e-9a04e1972703", "team_a": "Dila", "team_b": "Dinamo Batumi", "start_time": 1595782800.0, "url": "event/a4b1f902-2765-4699-8a0e-9a04e1972703", "team_a_image": "https://cdn.livetv323.me/img/teams/fullsize/32929.gif", "team_b_image": "https://cdn.livetv323.me/img/teams/fullsize/17612.gif", "match_country": "georgia", "league_name": "Georgia. Erovnuli Liga", "c": "1"}]}, {"league_id": "2e7a1e62-354e-49cf-a514-373fff22c309", "league_name": "Latvia. Virsliga", "league_country": "latvia", "matches": [{"id": "c9eb377a-53ae-4bbf-bf11-8e280b2d9b6b", "team_a": "Spartaks", "team_b": "METTA Latvijas Universit\u0414\u0403te", "start_time": "LIVE", "url": "event/c9eb377a-53ae-4bbf-bf11-8e280b2d9b6b", "team_a_image": "https://cdn.livetv323.me/img/teams/fullsize/33286.gif", "team_b_image": "https://cdn.livetv323.me/img/teams/fullsize/33289.gif", "match_country": "latvia", "league_name": "Latvia. Virsliga", "c": "0"}, {"id": "a36d329a-53ce-4366-a860-ed732595e64b", "team_a": "Liepaja", "team_b": "Daugavpils", "start_time": 1595779200.0, "url": "event/a36d329a-53ce-4366-a860-ed732595e64b", "team_a_image": "https://cdn.livetv323.me/img/teams/fullsize/33287.gif", "team_b_image": "https://cdn.livetv323.me/img/teams/fullsize/16835.gif", "match_country": "latvia", "league_name": "Latvia. Virsliga", "c": "1"}]}, {"league_id": "388744d2-ac2b-45fd-8519-ef9dd54d0e0f", "league_name": "Romania. Liga 2", "league_country": "romania", "matches": [{"id": "5bd19a29-5559-4387-9aac-e6ef61683e7a", "team_a": "UTA Arad", "team_b": "Rapid Bucure\u0219ti", "start_time": "LIVE", "url": "event/5bd19a29-5559-4387-9aac-e6ef61683e7a", "team_a_image": "https://cdn.livetv323.me/img/teams/fullsize/9982.gif", "team_b_image": "https://cdn.livetv323.me/img/teams/fullsize/3220.gif", "match_country": "romania", "league_name": "Romania. Liga 2", "c": "0"}]}, {"league_id": "d380ffde-8760-4d63-8fb5-90d9f8a9a44c", "league_name": "Liga 1", "league_country": "romania", "matches": [{"id": "c621349c-a29d-4d43-98cd-7b4f43dd98c6", "team_a": "Voluntari", "team_b": "ACS Sepsi OSK", "start_time": 1595782800.0, "url": "event/c621349c-a29d-4d43-98cd-7b4f43dd98c6", "team_a_image": "https://cdn.livetv323.me/img/teams/fullsize/43101.gif", "team_b_image": "https://cdn.livetv323.me/img/teams/fullsize/32964.gif", "match_country": "romania", "league_name": "Romania. Liga I", "c": "0"}, {"id": "53d2d9a4-fe14-4424-b8e8-26e1f2a064e2", "team_a": "Cluj", "team_b": "Botosani", "start_time": 1595786400.0, "url": "event/53d2d9a4-fe14-4424-b8e8-26e1f2a064e2", "team_a_image": "https://cdn.livetv323.me/img/teams/fullsize/32223.gif", "team_b_image": "https://cdn.livetv323.me/img/teams/fullsize/32217.gif", "match_country": "romania", "league_name": "Romania. Liga I", "c": "1"}]}, {"league_id": "16d0abec-402c-4666-b6c7-9853785011ba", "league_name": "Switzerland. Super League", "league_country": "switzerland", "matches": [{"id": "44900008-de3a-403a-814a-92429839614a", "team_a": "Basel", "team_b": "Lugano", "start_time": 1595781900.0, "url": "event/44900008-de3a-403a-814a-92429839614a", "team_a_image": "https://cdn.livetv323.me/img/teams/fullsize/32787.gif", "team_b_image": "https://cdn.livetv323.me/img/teams/fullsize/32898.gif", "match_country": "switzerland", "league_name": "Switzerland. Super League", "c": "0"}, {"id": "724bc837-3e2e-4b02-af2f-898b676b15ca", "team_a": "Servette", "team_b": "Xamax", "start_time": 1595781900.0, "url": "event/724bc837-3e2e-4b02-af2f-898b676b15ca", "team_a_image": "https://cdn.livetv323.me/img/teams/fullsize/17907.gif", "team_b_image": "https://cdn.livetv323.me/img/teams/fullsize/32897.gif", "match_country": "switzerland", "league_name": "Switzerland. Super League", "c": "1"}, {"id": "815ba060-9b6a-4d27-a063-5c9cef7bc798", "team_a": "Young Boys", "team_b": "Luzern", "start_time": "LIVE", "url": "event/815ba060-9b6a-4d27-a063-5c9cef7bc798", "team_a_image": "https://cdn.livetv323.me/img/teams/fullsize/32783.gif", "team_b_image": "https://cdn.livetv323.me/img/teams/fullsize/32789.gif", "match_country": "switzerland", "league_name": "Switzerland. Super League", "c": "1"}]}, {"league_id": "62c07f0b-f286-475d-97a9-4b473f9b7299", "league_name": "Ukraine. First League", "league_country": "ukraine", "matches": [{"id": "49c32dc5-5107-4c76-8fff-3d5268f7e9b1", "team_a": "Metalurh Z", "team_b": "Cherkaschyna-Akademia", "start_time": "LIVE", "url": "event/49c32dc5-5107-4c76-8fff-3d5268f7e9b1", "team_a_image": "https://cdn.livetv323.me/img/teams/fullsize/41366.gif", "team_b_image": "https://cdn.livetv323.me/img/teams/fullsize/32074.gif", "match_country": "ukraine", "league_name": "Ukraine. First League", "c": "0"}]}, {"league_id": "5dc3c423-5f28-41ce-9a73-a44ce86a9b8b", "league_name": "Qatar. Stars League", "league_country": "qatar", "matches": [{"id": "7e7ae80b-231f-4afd-908f-e1d60ada585e", "team_a": "Al Wakrah", "team_b": "Al Sailiya", "start_time": 1595771100.0, "url": "event/7e7ae80b-231f-4afd-908f-e1d60ada585e", "team_a_image": "https://cdn.livetv323.me/img/teams/fullsize/15307.gif", "team_b_image": "https://cdn.livetv323.me/img/teams/fullsize/33449.gif", "match_country": "qatar", "league_name": "Qatar. Stars League", "c": "1"}, {"id": "e77dde17-c58a-4a13-b425-8f21a54cdda6", "team_a": "Al Shahaniya", "team_b": "Al Ahli Doha", "start_time": 1595779200.0, "url": "event/e77dde17-c58a-4a13-b425-8f21a54cdda6", "team_a_image": "https://cdn.livetv323.me/img/teams/fullsize/33454.gif", "team_b_image": "https://cdn.livetv323.me/img/teams/fullsize/15289.gif", "match_country": "qatar", "league_name": "Qatar. Stars League", "c": "1"}]}, {"league_id": "0d817374-15ab-4e3b-b5f0-fa502bb3b2aa", "league_name": "Norway. Eliteserien", "league_country": "norway", "matches": [{"id": "2d3510f8-c5a7-4a02-9166-418283f81d01", "team_a": "Bodo-Glimt", "team_b": "Molde", "start_time": "LIVE", "url": "event/2d3510f8-c5a7-4a02-9166-418283f81d01", "team_a_image": "https://cdn.livetv323.me/img/teams/fullsize/32274.gif", "team_b_image": "https://cdn.livetv323.me/img/teams/fullsize/32265.gif", "match_country": "norway", "league_name": "Norway. Eliteserien", "c": "0"}, {"id": "72b81499-5dc7-4ab9-9a54-138489f0d76f", "team_a": "Viking", "team_b": "Sarpsborg 08", "start_time": "LIVE", "url": "event/72b81499-5dc7-4ab9-9a54-138489f0d76f", "team_a_image": "https://cdn.livetv323.me/img/teams/fullsize/17766.gif", "team_b_image": "https://cdn.livetv323.me/img/teams/fullsize/32268.gif", "match_country": "norway", "league_name": "Norway. Eliteserien", "c": "1"}, {"id": "6a3c59a8-445a-4882-ae03-2e0e5e8418e0", "team_a": "Valerenga", "team_b": "Stromsgodset", "start_time": "LIVE", "url": "event/6a3c59a8-445a-4882-ae03-2e0e5e8418e0", "team_a_image": "https://cdn.livetv323.me/img/teams/fullsize/32271.gif", "team_b_image": "https://cdn.livetv323.me/img/teams/fullsize/32273.gif", "match_country": "norway", "league_name": "Norway. Eliteserien", "c": "1"}, {"id": "e53cf3ff-9e1f-4459-a3f1-9dd4243cc620", "team_a": "Sandefjord", "team_b": "Mjondalen", "start_time": "LIVE", "url": "event/e53cf3ff-9e1f-4459-a3f1-9dd4243cc620", "team_a_image": "https://cdn.livetv323.me/img/teams/fullsize/32277.gif", "team_b_image": "https://cdn.livetv323.me/img/teams/fullsize/17765.gif", "match_country": "norway", "league_name": "Norway. Eliteserien", "c": "1"}, {"id": "904d3712-f639-4b56-9816-fe42fac71161", "team_a": "IK Start", "team_b": "Stabaek", "start_time": "LIVE", "url": "event/904d3712-f639-4b56-9816-fe42fac71161", "team_a_image": "https://cdn.livetv323.me/img/teams/fullsize/32972.gif", "team_b_image": "https://cdn.livetv323.me/img/teams/fullsize/32276.gif", "match_country": "norway", "league_name": "Norway. Eliteserien", "c": "0"}, {"id": "460551ee-7b88-4218-843f-1aa83469b31c", "team_a": "Haugesund", "team_b": "Rosenborg", "start_time": 1595788200.0, "url": "event/460551ee-7b88-4218-843f-1aa83469b31c", "team_a_image": "https://cdn.livetv323.me/img/teams/fullsize/32971.gif", "team_b_image": "https://cdn.livetv323.me/img/teams/fullsize/32264.gif", "match_country": "norway", "league_name": "Norway. Eliteserien", "c": "1"}]}, {"league_id": "dc76012c-fad4-4eca-8c3f-882927f1bc41", "league_name": "Norway. 1. Divisjon", "league_country": "norway", "matches": [{"id": "fcc4466b-5069-4667-8ea2-cff12a30cbd0", "team_a": "Grorud", "team_b": "Jerv", "start_time": 1595865600.0, "url": "event/fcc4466b-5069-4667-8ea2-cff12a30cbd0", "team_a_image": "https://cdn.livetv323.me/img/teams/fullsize/39755.gif", "team_b_image": "https://cdn.livetv323.me/img/teams/fullsize/20884.gif", "match_country": "norway", "league_name": "Norway. 1. Divisjon", "c": "0"}, {"id": "801bb963-0844-4c20-a861-3de9bc0652ab", "team_a": "KFUM", "team_b": "Sogndal", "start_time": 1595865600.0, "url": "event/801bb963-0844-4c20-a861-3de9bc0652ab", "team_a_image": "https://cdn.livetv323.me/img/teams/fullsize/21539.gif", "team_b_image": "https://cdn.livetv323.me/img/teams/fullsize/4860.gif", "match_country": "norway", "league_name": "Norway. 1. Divisjon", "c": "0"}, {"id": "c9eb45ad-a162-4c6c-9984-b19b5140c33f", "team_a": "Raufoss", "team_b": "Kongsvinger", "start_time": 1595865600.0, "url": "event/c9eb45ad-a162-4c6c-9984-b19b5140c33f", "team_a_image": "https://cdn.livetv323.me/img/teams/fullsize/15310.gif", "team_b_image": "https://cdn.livetv323.me/img/teams/fullsize/39794.gif", "match_country": "norway", "league_name": "Norway. 1. Divisjon", "c": "0"}, {"id": "43dd61f7-9182-493d-9830-7fefa5034aa2", "team_a": "Sandnes Ulf", "team_b": "Ullensaker / Kisa", "start_time": 1595865600.0, "url": "event/43dd61f7-9182-493d-9830-7fefa5034aa2", "team_a_image": "https://cdn.livetv323.me/img/teams/fullsize/10927.gif", "team_b_image": "https://cdn.livetv323.me/img/teams/fullsize/17758.gif", "match_country": "norway", "league_name": "Norway. 1. Divisjon", "c": "0"}, {"id": "4507c474-f9d8-47d8-9673-1eb8c9a9e2ce", "team_a": "Stjordals-Blink", "team_b": "Strommen", "start_time": 1595865600.0, "url": "event/4507c474-f9d8-47d8-9673-1eb8c9a9e2ce", "team_a_image": "https://cdn.livetv323.me/img/teams/fullsize/22955.gif", "team_b_image": "https://cdn.livetv323.me/img/teams/fullsize/17762.gif", "match_country": "norway", "league_name": "Norway. 1. Divisjon", "c": "0"}, {"id": "e16ef817-e130-4ff2-b126-bff84bed6ec4", "team_a": "Tromso", "team_b": "Oygarden", "start_time": 1595865600.0, "url": "event/e16ef817-e130-4ff2-b126-bff84bed6ec4", "team_a_image": "https://cdn.livetv323.me/img/teams/fullsize/32269.gif", "team_b_image": "https://cdn.livetv323.me/img/teams/fullsize/39562.gif", "match_country": "norway", "league_name": "Norway. 1. Divisjon", "c": "0"}, {"id": "584764e5-de9a-49f6-b935-0b74018bf5b9", "team_a": "Asane", "team_b": "Lillestrom", "start_time": 1595865600.0, "url": "event/584764e5-de9a-49f6-b935-0b74018bf5b9", "team_a_image": "https://cdn.livetv323.me/img/teams/fullsize/20885.gif", "team_b_image": "https://cdn.livetv323.me/img/teams/fullsize/32275.gif", "match_country": "norway", "league_name": "Norway. 1. Divisjon", "c": "0"}]}, {"league_id": "345171db-3756-4097-a6c7-00cb770c18d8", "league_name": "Iceland. Urvalsdeild", "league_country": "iceland", "matches": [{"id": "1201e7aa-a2d4-495e-945f-fe0cee223f69", "team_a": "Akureyri", "team_b": "KR Reykjavik", "start_time": 1595779200.0, "url": "event/1201e7aa-a2d4-495e-945f-fe0cee223f69", "team_a_image": "https://cdn.livetv323.me/img/teams/fullsize/33087.gif", "team_b_image": "https://cdn.livetv323.me/img/teams/fullsize/32712.gif", "match_country": "iceland", "league_name": "Iceland. Urvalsdeild", "c": "1"}, {"id": "409e5eb3-b648-41a6-bf86-6e7d9f1bc668", "team_a": "Brei\u00f0ablik UBK", "team_b": "IA Akranes", "start_time": 1595790900.0, "url": "event/409e5eb3-b648-41a6-bf86-6e7d9f1bc668", "team_a_image": "https://cdn.livetv323.me/img/teams/fullsize/32709.gif", "team_b_image": "https://cdn.livetv323.me/img/teams/fullsize/11256.gif", "match_country": "iceland", "league_name": "Iceland. Urvalsdeild", "c": "0"}]}, {"league_id": "2c349559-937e-47bf-b616-815c7210ac37", "league_name": "Slovenia. PrvaLiga / \nPlay-off for 1st league.", "league_country": "slovenia", "matches": [{"id": "881ceb85-a1fe-42c1-829f-c11a878601b8", "team_a": "Gorica", "team_b": "Triglav", "start_time": 1595779200.0, "url": "event/881ceb85-a1fe-42c1-829f-c11a878601b8", "team_a_image": "https://cdn.livetv323.me/img/teams/fullsize/6306.gif", "team_b_image": "https://cdn.livetv323.me/img/teams/fullsize/36620.gif", "match_country": "slovenia", "league_name": "Slovenia. PrvaLiga / \nPlay-off for 1st league.", "c": "1"}]}, {"league_id": "4f7eee47-d764-46a9-8ec1-17bd2d624a37", "league_name": "Moldova. National Division", "league_country": "moldova", "matches": [{"id": "33b11c60-3aa8-41f0-89a1-f7d18bde2937", "team_a": "Sheriff", "team_b": "Dinamo-Auto", "start_time": 1595784600.0, "url": "event/33b11c60-3aa8-41f0-89a1-f7d18bde2937", "team_a_image": "https://cdn.livetv323.me/img/teams/fullsize/33824.gif", "team_b_image": "https://cdn.livetv323.me/img/teams/fullsize/39751.gif", "match_country": "moldova", "league_name": "Moldova. National Division", "c": "1"}, {"id": "d59f6305-d11c-406e-97b8-f1cfd2fc52bf", "team_a": "Sfintul Gheorghe", "team_b": "Floresti", "start_time": 1595862000.0, "url": "event/d59f6305-d11c-406e-97b8-f1cfd2fc52bf", "team_a_image": "https://cdn.livetv323.me/img/teams/fullsize/33829.gif", "team_b_image": "https://cdn.livetv323.me/img/teams/fullsize/35229.gif", "match_country": "moldova", "league_name": "Moldova. National Division", "c": "1"}]}, {"league_id": "e496ffef-852d-4d83-8842-7c918ec094e0", "league_name": "Greece. Cup / \nFinal.", "league_country": "greece", "matches": [{"id": "f59e9ef0-c730-42bd-994d-23b76b602c05", "team_a": "AEK", "team_b": "Olympiacos", "start_time": 1595786400.0, "url": "event/f59e9ef0-c730-42bd-994d-23b76b602c05", "team_a_image": "https://cdn.livetv323.me/img/teams/fullsize/32467.gif", "team_b_image": "https://cdn.livetv323.me/img/teams/fullsize/33012.gif", "match_country": "greece", "league_name": "Greece. Cup / \nFinal.", "c": "1"}]}, {"league_id": "4c88775f-64a4-4108-926f-261f0ae7f5e5", "league_name": "Paraguay. Primera Division", "league_country": "paraguay", "matches": [{"id": "0dd255dc-585e-4928-94f0-3d3996dbcd92", "team_a": "Nacional Asuncion", "team_b": "Sportivo Luqueno", "start_time": 1595793600.0, "url": "event/0dd255dc-585e-4928-94f0-3d3996dbcd92", "team_a_image": "https://cdn.livetv323.me/img/teams/fullsize/33594.gif", "team_b_image": "https://cdn.livetv323.me/img/teams/fullsize/33593.gif", "match_country": "paraguay", "league_name": "Paraguay. Primera Division", "c": "1"}, {"id": "25c2a26c-3e63-482b-9bb7-8f57e67a1c88", "team_a": "Club Olimpia", "team_b": "Sol de America", "start_time": 1595802600.0, "url": "event/25c2a26c-3e63-482b-9bb7-8f57e67a1c88", "team_a_image": "https://cdn.livetv323.me/img/teams/fullsize/33589.gif", "team_b_image": "https://cdn.livetv323.me/img/teams/fullsize/33598.gif", "match_country": "paraguay", "league_name": "Paraguay. Primera Division", "c": "1"}]}, {"league_id": "3f8df23c-da3d-4e28-b069-7c6dcfb12cf7", "league_name": "Australia. A-League", "league_country": "australia", "matches": [{"id": "064ab007-6623-41dc-880a-53544a98b025", "team_a": "Central Coast Mariners", "team_b": "Western Sydney Wanderers", "start_time": 1595842200.0, "url": "event/064ab007-6623-41dc-880a-53544a98b025", "team_a_image": "https://cdn.livetv323.me/img/teams/fullsize/32667.gif", "team_b_image": "https://cdn.livetv323.me/img/teams/fullsize/32664.gif", "match_country": "australia", "league_name": "Australia. A-League", "c": "0"}]}, {"league_id": "883c56da-3ef3-4429-a328-8600d541412d", "league_name": "Australia. A League", "league_country": "australia", "matches": [{"id": "fa5eb50f-97be-483e-b987-878aaeb86f0a", "team_a": "Central Coast Mariners Academy", "team_b": "Western Sydney Wanderers", "start_time": 1595842200.0, "url": "event/fa5eb50f-97be-483e-b987-878aaeb86f0a", "team_a_image": null, "team_b_image": null, "match_country": "australia", "league_name": "Australia. A League", "c": "1"}]}, {"league_id": "77a36c0f-ba40-4b76-99a8-02215a8ef9de", "league_name": "China. Super League", "league_country": "china", "matches": [{"id": "f2385a2e-5abd-4203-93b5-690223aa1e9e", "team_a": "Tianjin Teda", "team_b": "Shanghai SIPG", "start_time": 1595849700.0, "url": "event/f2385a2e-5abd-4203-93b5-690223aa1e9e", "team_a_image": "https://cdn.livetv323.me/img/teams/fullsize/32917.gif", "team_b_image": "https://cdn.livetv323.me/img/teams/fullsize/32913.gif", "match_country": "china", "league_name": "China. Super League", "c": "1"}]}, {"league_id": "c84a9bd4-5bb3-428c-9637-75e3a327139a", "league_name": "Meistaradeildin", "league_country": "faroe-islands", "matches": [{"id": "69f08055-78ae-4472-8f77-f8bc228f4891", "team_a": "Runavik", "team_b": "Klaksvik", "start_time": 1595858400.0, "url": "event/69f08055-78ae-4472-8f77-f8bc228f4891", "team_a_image": "https://cdn.livetv323.me/img/teams/fullsize/12783.gif", "team_b_image": "https://cdn.livetv323.me/img/teams/fullsize/15502.gif", "match_country": "faroe-islands", "league_name": "Faroe Islands. Premier League", "c": "1"}]}, {"league_id": "0c8cf7d3-791e-4971-baec-02a134e5af78", "league_name": "Northern Ireland. Cup / \nSemifinal.", "league_country": "northern-ireland", "matches": [{"id": "4eadc895-c11a-4f51-be22-96eca1c5803a", "team_a": "Ballymena Utd", "team_b": "Coleraine", "start_time": 1595862000.0, "url": "event/4eadc895-c11a-4f51-be22-96eca1c5803a", "team_a_image": "https://cdn.livetv323.me/img/teams/fullsize/33094.gif", "team_b_image": "https://cdn.livetv323.me/img/teams/fullsize/32792.gif", "match_country": "northern-ireland", "league_name": "Northern Ireland. Cup / \nSemifinal.", "c": "1"}]}, {"league_id": "8f14d9f2-d564-48ee-b931-e2f74e3fdd8c", "league_name": "Meistriliiga", "league_country": "estonia", "matches": [{"id": "02e4d763-de47-423f-9a4d-3b9b57905a8f", "team_a": "Kuressaare", "team_b": "Tallinna Kalev", "start_time": 1595865600.0, "url": "event/02e4d763-de47-423f-9a4d-3b9b57905a8f", "team_a_image": "https://cdn.livetv323.me/img/teams/fullsize/33002.gif", "team_b_image": "https://cdn.livetv323.me/img/teams/fullsize/33001.gif", "match_country": "estonia", "league_name": "Estonia. Meistriliiga", "c": "0"}]}, {"league_id": "7cc3dd27-e38b-4595-9bce-e73cbc49917b", "league_name": "Iran. Pro League", "league_country": "iran", "matches": [{"id": "40d72e5b-b639-4adf-826b-2029d917eaf6", "team_a": "Pars Jam Bushehr", "team_b": "Esteghlal", "start_time": 1595865600.0, "url": "event/40d72e5b-b639-4adf-826b-2029d917eaf6", "team_a_image": "https://cdn.livetv323.me/img/teams/fullsize/33338.gif", "team_b_image": "https://cdn.livetv323.me/img/teams/fullsize/33340.gif", "match_country": "iran", "league_name": "Iran. Pro League", "c": "0"}]}, {"league_id": "e7276c54-6208-4850-9593-2888c086439e", "league_name": "Club Friendlies", "league_country": "unknown", "matches": [{"id": "3211729a-7930-4e48-bd7f-9ba2f5841e78", "team_a": "Kuban Holding", "team_b": "Yenisey Krasnoyarsk", "start_time": "LIVE", "url": "event/3211729a-7930-4e48-bd7f-9ba2f5841e78", "team_a_image": null, "team_b_image": null, "match_country": "unknown", "league_name": "Club Friendlies", "c": "1"}, {"id": "261aeac9-106f-4c2c-bf95-2b4cf0669c0e", "team_a": "Partizan Belgrade", "team_b": "Proleter Novi Sad", "start_time": "LIVE", "url": "event/261aeac9-106f-4c2c-bf95-2b4cf0669c0e", "team_a_image": null, "team_b_image": null, "match_country": "unknown", "league_name": "Club Friendlies", "c": "0"}]}, {"league_id": "57e0ee23-368d-4d2d-b72c-002b6e1c6672", "league_name": "Slovakia Cup", "league_country": "unknown", "matches": [{"id": "e6313253-4bad-4167-8d21-212f451bc155", "team_a": "05 Levoca", "team_b": "Pokrok SEZ Krompachy", "start_time": "LIVE", "url": "event/e6313253-4bad-4167-8d21-212f451bc155", "team_a_image": null, "team_b_image": null, "match_country": "unknown", "league_name": "Slovakia Cup", "c": "1"}]}, {"league_id": "b0a88c96-e559-44a0-a961-5b014f05238e", "league_name": "Friendly Match", "league_country": "unknown", "matches": [{"id": "db6ad2dd-bdf8-4c48-96e2-ae4394acadc1", "team_a": "Dynamo Kiev U21", "team_b": "Veres", "start_time": 1595772000.0, "url": "event/db6ad2dd-bdf8-4c48-96e2-ae4394acadc1", "team_a_image": "https://cdn.livetv323.me/img/teams/fullsize/32619.gif", "team_b_image": "https://cdn.livetv323.me/img/teams/fullsize/21318.gif", "match_country": "unknown", "league_name": "Friendly Match", "c": "1"}, {"id": "589f8615-e291-47d9-9f6c-039a3408458a", "team_a": "Zhytlobud-2 (W)", "team_b": "Zhytlobud-1 (W)", "start_time": 1595775600.0, "url": "event/589f8615-e291-47d9-9f6c-039a3408458a", "team_a_image": null, "team_b_image": null, "match_country": "unknown", "league_name": "Friendly Match", "c": "1"}]}, {"league_id": "864623f3-8992-4168-be74-dd7666ab0c7b", "league_name": "Women. Friendly Tournament / \nBelarus. Premier Division.", "league_country": "unknown", "matches": [{"id": "28292576-2686-4e46-9fa1-603212e0412c", "team_a": "Minsk (W)", "team_b": "Bobruichanka (W)", "start_time": 1595772000.0, "url": "event/28292576-2686-4e46-9fa1-603212e0412c", "team_a_image": "https://cdn.livetv323.me/img/teams/fullsize/43645.gif", "team_b_image": "https://cdn.livetv323.me/img/teams/fullsize/43440.gif", "match_country": "unknown", "league_name": "Women. Friendly Tournament / \nBelarus. Premier Division.", "c": "1"}, {"id": "89fab8d4-6241-410e-ab9f-dfe2563dd8c6", "team_a": "Dnepr Mogilev (W)", "team_b": "ABFF U19 (W)", "start_time": 1595779200.0, "url": "event/89fab8d4-6241-410e-ab9f-dfe2563dd8c6", "team_a_image": "https://cdn.livetv323.me/img/teams/fullsize/42521.gif", "team_b_image": "https://cdn.livetv323.me/img/teams/fullsize/43478.gif", "match_country": "unknown", "league_name": "Women. Friendly Tournament / \nBelarus. Premier Division.", "c": "1"}, {"id": "0568c823-22cc-4f6f-929d-df30d900fd46", "team_a": "Zorka-BDU (W)", "team_b": "Dinamo Minsk (W)", "start_time": 1595858400.0, "url": "event/0568c823-22cc-4f6f-929d-df30d900fd46", "team_a_image": "https://cdn.livetv323.me/img/teams/fullsize/43441.gif", "team_b_image": "https://cdn.livetv323.me/img/teams/fullsize/43465.gif", "match_country": "unknown", "league_name": "Women. Friendly Tournament / \nBelarus. Premier Division.", "c": "1"}, {"id": "654dbfee-e78b-41f2-a5c3-a8ad5fe04de3", "team_a": "BOTSOR (W)", "team_b": "Neman (W)", "start_time": 1595865600.0, "url": "event/654dbfee-e78b-41f2-a5c3-a8ad5fe04de3", "team_a_image": "https://cdn.livetv323.me/img/teams/fullsize/43466.gif", "team_b_image": "https://cdn.livetv323.me/img/teams/fullsize/43453.gif", "match_country": "unknown", "league_name": "Women. Friendly Tournament / \nBelarus. Premier Division.", "c": "0"}]}, {"league_id": "5df27f11-7018-4b89-aa7a-1f4cec906f4e", "league_name": "USA. Women. NWSL", "league_country": "unknown", "matches": [{"id": "9a728927-100e-4f03-8781-d7d3aa3a0f7a", "team_a": "Chicago Red Stars (W)", "team_b": "Houston Dash (W)", "start_time": 1595781000.0, "url": "event/9a728927-100e-4f03-8781-d7d3aa3a0f7a", "team_a_image": "https://cdn.livetv323.me/img/teams/fullsize/31409.gif", "team_b_image": "https://cdn.livetv323.me/img/teams/fullsize/31414.gif", "match_country": "unknown", "league_name": "USA. Women. NWSL", "c": "0"}]}, {"league_id": "9f09f52d-0324-4355-8617-e5b675f495f4", "league_name": "USA. USL", "league_country": "unknown", "matches": [{"id": "a6c247cc-00b3-49e2-86af-bd8e3f616e1a", "team_a": "New York Red Bulls II", "team_b": "Pittsburgh Riverhounds", "start_time": 1595797200.0, "url": "event/a6c247cc-00b3-49e2-86af-bd8e3f616e1a", "team_a_image": "https://cdn.livetv323.me/img/teams/fullsize/33688.gif", "team_b_image": "https://cdn.livetv323.me/img/teams/fullsize/33684.gif", "match_country": "unknown", "league_name": "USA. USL", "c": "1"}, {"id": "4a217d3f-fa0c-41cd-86ac-53dbff38d1ae", "team_a": "Saint Louis FC", "team_b": "Indy Eleven", "start_time": 1595797200.0, "url": "event/4a217d3f-fa0c-41cd-86ac-53dbff38d1ae", "team_a_image": "https://cdn.livetv323.me/img/teams/fullsize/33706.gif", "team_b_image": "https://cdn.livetv323.me/img/teams/fullsize/33687.gif", "match_country": "unknown", "league_name": "USA. USL", "c": "1"}, {"id": "30f20abe-27d5-4db4-9363-db2e969d10ee", "team_a": "Portland II", "team_b": "Reno 1868", "start_time": 1595811600.0, "url": "event/30f20abe-27d5-4db4-9363-db2e969d10ee", "team_a_image": "https://cdn.livetv323.me/img/teams/fullsize/33702.gif", "team_b_image": "https://cdn.livetv323.me/img/teams/fullsize/33704.gif", "match_country": "unknown", "league_name": "USA. USL", "c": "1"}]}, {"league_id": "1c9c36ed-e973-4d6f-af5c-e6d205ddd56a", "league_name": "USA. MLS / \nRound of 16.", "league_country": "unknown", "matches": [{"id": "abc637a7-a6fd-4d76-904a-2dca8b1af986", "team_a": "Toronto", "team_b": "New York City", "start_time": 1595809800.0, "url": "event/abc637a7-a6fd-4d76-904a-2dca8b1af986", "team_a_image": "https://cdn.livetv323.me/img/teams/fullsize/33929.gif", "team_b_image": "https://cdn.livetv323.me/img/teams/fullsize/32855.gif", "match_country": "unknown", "league_name": "USA. MLS / \nRound of 16.", "c": "1"}, {"id": "74488c3a-bc8e-4e7a-b699-df3681ab433c", "team_a": "Kansas City", "team_b": "Vancouver", "start_time": 1595818800.0, "url": "event/74488c3a-bc8e-4e7a-b699-df3681ab433c", "team_a_image": "https://cdn.livetv323.me/img/teams/fullsize/32864.gif", "team_b_image": "https://cdn.livetv323.me/img/teams/fullsize/32869.gif", "match_country": "unknown", "league_name": "USA. MLS / \nRound of 16.", "c": "1"}]}, {"league_id": "55fd6372-40f0-4574-b469-897d7a77fd00", "league_name": "Qatar Championship", "league_country": "unknown", "matches": [{"id": "0e185d8f-2c74-49f5-96ef-0e93fd3464ff", "team_a": "Al-Shahaniya", "team_b": "Al Ahli Doha", "start_time": "LIVE", "url": "event/0e185d8f-2c74-49f5-96ef-0e93fd3464ff", "team_a_image": null, "team_b_image": null, "match_country": "unknown", "league_name": "Qatar Championship", "c": "0"}]}, {"league_id": "505cfe0d-e085-47f3-bb5a-dd91007b7e67", "league_name": "USA. MLS", "league_country": "unknown", "matches": [{"id": "abc637a7-a6fd-4d76-904a-2dca8b1af986", "team_a": "Toronto", "team_b": "New York City", "start_time": 1595809800.0, "url": "event/abc637a7-a6fd-4d76-904a-2dca8b1af986", "team_a_image": null, "team_b_image": null, "match_country": "unknown", "league_name": "USA. MLS", "c": "1"}, {"id": "ef62c0ff-c283-47f5-bb24-5db888368fbe", "team_a": "Sporting Kansas City", "team_b": "Vancouver Whitecaps", "start_time": 1595818800.0, "url": "event/ef62c0ff-c283-47f5-bb24-5db888368fbe", "team_a_image": null, "team_b_image": null, "match_country": "unknown", "league_name": "USA. MLS", "c": "1"}]}, {"league_id": "4416d9d7-868c-4f9d-bc23-0f7d8a27931c", "league_name": "USA. MLS is Back Tournament", "league_country": "unknown", "matches": [{"id": "2be599a8-7e81-496b-af50-ae349f6bf9ce", "team_a": "Toronto FC", "team_b": "New York City FC", "start_time": 1595809800.0, "url": "event/2be599a8-7e81-496b-af50-ae349f6bf9ce", "team_a_image": null, "team_b_image": null, "match_country": "unknown", "league_name": "USA. MLS is Back Tournament", "c": "1"}, {"id": "a7441e59-d087-4c63-934f-77f658be491c", "team_a": "Sporting Kansas City", "team_b": "Vancouver Whitecaps FC", "start_time": 1595818800.0, "url": "event/a7441e59-d087-4c63-934f-77f658be491c", "team_a_image": null, "team_b_image": null, "match_country": "unknown", "league_name": "USA. MLS is Back Tournament", "c": "1"}]}]